{"schema":1,"type":"practice","session":"fp3","drivers":[{"code":"RIC","ref":"ricciardo","name":"Daniel Ricciardo","team":"Renault","teamId":"renault","color":"#888888","position":null,"grid":null,"status":null,"gap":null,"points":null},{"code":"NOR","ref":"norris","name":"Lando Norris","team":"McLaren","teamId":"mclaren","color":"#FF8000","position":null,"grid":null,"status":null,"gap":null,"points":null},{"code":"VET","ref":"vettel","name":"Sebastian Vettel","team":"Ferrari","teamId":"ferrari","color":"#E80020","position":null,"grid":null,"status":null,"gap":null,"points":null},{"code":"LAT","ref":"latifi","name":"Nicholas Latifi","team":"Williams","teamId":"williams","color":"#64C4FF","position":null,"grid":null,"status":null,"gap":null,"points":null},{"code":"RAI","ref":"raikkonen","name":"Kimi Räikkönen","team":"Alfa Romeo Racing","teamId":"alfa","color":"#888888","position":null,"grid":null,"status":null,"gap":null,"points":null},{"code":"GRO","ref":"grosjean","name":"Romain Grosjean","team":"Haas F1 Team","teamId":"haas","color":"#B6BABD","position":null,"grid":null,"status":null,"gap":null,"points":null},{"code":"GAS","ref":"gasly","name":"Pierre Gasly","team":"AlphaTauri","teamId":"alphatauri","color":"#888888","position":null,"grid":null,"status":null,"gap":null,"points":null},{"code":"PER","ref":"perez","name":"Sergio Perez","team":"Racing Point","teamId":"racing_point","color":"#888888","position":null,"grid":null,"status":null,"gap":null,"points":null},{"code":"LEC","ref":"leclerc","name":"Charles Leclerc","team":"Ferrari","teamId":"ferrari","color":"#E80020","position":null,"grid":null,"status":null,"gap":null,"points":null},{"code":"STR","ref":"stroll","name":"Lance Stroll","team":"Racing Point","teamId":"racing_point","color":"#888888","position":null,"grid":null,"status":null,"gap":null,"points":null},{"code":"MAG","ref":"kevin_magnussen","name":"Kevin Magnussen","team":"Haas F1 Team","teamId":"haas","color":"#B6BABD","position":null,"grid":null,"status":null,"gap":null,"points":null},{"code":"ALB","ref":"albon","name":"Alexander Albon","team":"Red Bull Racing","teamId":"redbull","color":"#3671C6","position":null,"grid":null,"status":null,"gap":null,"points":null},{"code":"KVY","ref":"kvyat","name":"Daniil Kvyat","team":"AlphaTauri","teamId":"alphatauri","color":"#888888","position":null,"grid":null,"status":null,"gap":null,"points":null},{"code":"OCO","ref":"ocon","name":"Esteban Ocon","team":"Renault","teamId":"renault","color":"#888888","position":null,"grid":null,"status":null,"gap":null,"points":null},{"code":"VER","ref":"max_verstappen","name":"Max Verstappen","team":"Red Bull Racing","teamId":"redbull","color":"#3671C6","position":null,"grid":null,"status":null,"gap":null,"points":null},{"code":"HAM","ref":"hamilton","name":"Lewis Hamilton","team":"Mercedes","teamId":"mercedes","color":"#27F4D2","position":null,"grid":null,"status":null,"gap":null,"points":null},{"code":"SAI","ref":"sainz","name":"Carlos Sainz","team":"McLaren","teamId":"mclaren","color":"#FF8000","position":null,"grid":null,"status":null,"gap":null,"points":null},{"code":"RUS","ref":"russell","name":"George Russell","team":"Williams","teamId":"williams","color":"#64C4FF","position":null,"grid":null,"status":null,"gap":null,"points":null},{"code":"BOT","ref":"bottas","name":"Valtteri Bottas","team":"Mercedes","teamId":"mercedes","color":"#27F4D2","position":null,"grid":null,"status":null,"gap":null,"points":null},{"code":"GIO","ref":"giovinazzi","name":"Antonio Giovinazzi","team":"Alfa Romeo Racing","teamId":"alfa","color":"#888888","position":null,"grid":null,"status":null,"gap":null,"points":null}],"weather":{"airMin":17.7,"airMax":20.3,"trackMin":22.0,"trackMax":30.4,"windAvg":4.453,"windDirDeg":142,"rain":false,"samples":[[0.8,17.7,22.0,2.52,0],[1.8,17.8,22.1,4.32,0],[2.8,17.8,22.2,2.88,0],[3.8,17.8,22.3,2.52,0],[4.8,17.8,22.3,2.16,0],[5.8,17.9,22.3,2.88,0],[6.8,18.0,22.8,2.52,0],[7.8,18.0,22.9,3.24,0],[8.8,18.0,23.1,5.4,0],[9.8,18.0,23.1,2.88,0],[10.8,18.2,23.2,4.32,0],[11.8,18.2,23.5,3.24,0],[12.8,18.2,23.5,3.6,0],[13.8,18.2,23.8,1.8,0],[14.8,18.3,23.8,0.0,0],[15.8,18.5,23.8,0.0,0],[16.8,18.6,24.0,2.52,0],[17.8,18.7,24.5,2.52,0],[18.8,18.7,24.5,4.32,0],[19.8,18.7,24.5,4.32,0],[20.8,18.6,24.5,1.8,0],[21.8,18.6,24.5,2.52,0],[22.8,18.8,24.6,3.24,0],[23.8,19.0,25.0,2.88,0],[24.8,19.0,25.1,2.52,0],[25.8,19.0,25.3,2.52,0],[26.8,19.0,25.5,3.96,0],[27.8,19.0,25.6,3.96,0],[28.8,19.0,25.7,3.6,0],[29.8,19.0,25.7,4.32,0],[30.8,18.8,26.0,5.04,0],[31.8,18.9,26.0,1.8,0],[32.8,19.0,26.1,4.68,0],[33.8,18.9,26.5,7.2,0],[34.8,18.8,26.6,6.12,0],[35.8,18.9,26.6,6.48,0],[36.8,19.0,26.5,5.04,0],[37.8,19.1,26.6,6.12,0],[38.8,19.1,26.7,3.96,0],[39.8,19.2,27.0,7.56,0],[40.8,19.2,27.0,5.4,0],[41.8,19.1,27.0,6.12,0],[42.8,19.1,27.0,3.96,0],[43.8,19.3,27.1,7.56,0],[44.8,19.3,27.4,11.16,0],[45.8,19.4,27.7,8.28,0],[46.8,19.6,27.9,6.48,0],[47.8,19.7,27.9,6.12,0],[48.8,19.6,28.0,6.84,0],[49.8,19.6,28.2,10.08,0],[50.8,19.8,28.2,4.32,0],[51.8,19.9,28.3,3.6,0],[52.8,19.9,28.4,7.2,0],[53.8,19.9,28.5,7.92,0],[54.8,20.0,28.6,2.88,0],[55.8,20.2,28.9,3.24,0],[56.8,20.0,29.0,5.04,0],[57.8,19.9,29.0,5.4,0],[58.8,19.9,28.8,3.96,0],[59.8,19.9,28.9,3.96,0],[60.8,20.1,29.0,2.52,0],[61.8,20.3,29.4,1.44,0],[62.8,20.1,29.6,4.32,0],[63.8,19.9,29.1,5.76,0],[64.8,19.8,29.1,6.84,0],[65.8,19.7,29.3,5.76,0],[66.8,19.6,29.3,6.84,0],[67.8,19.5,29.4,6.84,0],[68.8,19.5,29.4,6.12,0],[69.8,19.7,29.6,2.88,0],[70.8,19.8,29.8,4.32,0],[71.8,19.9,30.0,4.32,0],[72.8,19.9,30.0,5.4,0],[73.8,19.8,30.0,7.92,0],[74.8,19.7,30.0,2.88,0],[75.8,19.8,30.4,1.44,0]]},"order":[{"code":"BOT","t":76.654},{"code":"VER","t":76.659},{"code":"HAM","t":76.68},{"code":"GAS","t":76.93},{"code":"ALB","t":76.949},{"code":"LEC","t":77.229},{"code":"SAI","t":77.238},{"code":"PER","t":77.297},{"code":"NOR","t":77.478},{"code":"OCO","t":77.666},{"code":"VET","t":77.685},{"code":"KVY","t":77.72},{"code":"RAI","t":77.922},{"code":"RIC","t":77.935},{"code":"RUS","t":78.032},{"code":"STR","t":78.09},{"code":"GRO","t":78.132},{"code":"GIO","t":78.201},{"code":"MAG","t":78.287},{"code":"LAT","t":78.397}],"lapsAll":{"ALB":[[36.67,92.42,"M"],[38.21,77.921,"M"],[39.5,91.571,"M"],[41.03,77.179,"M"],[42.32,93.662,"M"],[43.88,77.117,"M"],[45.16,95.542,"M"],[46.76,92.616,"M"],[48.3,76.949,"M"],[58.7,90.174,"S"],[60.2,77.804,"S"],[61.5,102.319,"S"],[63.21,88.337,"S"],[64.68,78.575,"S"],[65.99,113.451,"S"],[67.88,100.526,"S"],[69.55,77.627,"S"],[70.85,96.751,"S"],[72.46,77.327,"S"]],"BOT":[[24.35,77.888,"S"],[25.65,96.528,"S"],[27.26,82.699,"S"],[28.64,77.578,"S"],[34.69,79.73,"S"],[44.61,93.639,"S"],[46.17,83.416,"S"],[47.56,92.999,"S"],[49.11,76.654,"S"],[59.01,81.198,"S"],[60.36,80.809,"S"],[61.71,81.21,"S"],[63.06,81.026,"S"],[64.41,80.894,"S"],[65.76,85.885,"S"],[67.19,85.703,"S"],[68.62,80.885,"S"],[69.97,86.822,"S"],[71.41,83.438,"S"]],"GAS":[[30.45,77.905,"S"],[31.75,102.445,"S"],[33.45,77.047,"S"],[34.74,98.056,"S"],[36.37,88.162,"S"],[37.84,76.93,"S"],[47.23,80.301,"S"],[48.57,80.731,"S"],[49.91,80.73,"S"],[51.26,80.821,"S"],[52.6,80.69,"S"],[53.95,82.966,"S"],[55.33,81.982,"S"],[66.59,101.449,"S"],[68.28,77.517,"S"],[69.58,102.118,"S"],[71.28,77.585,"S"]],"GIO":[[28.06,79.602,"S"],[29.38,111.123,"S"],[31.24,79.226,"S"],[32.56,103.37,"S"],[34.28,78.844,"S"],[35.59,102.564,"S"],[37.3,78.371,"S"],[38.61,107.65,"S"],[40.4,78.322,"S"],[41.71,99.982,"S"],[43.37,78.221,"S"],[66.77,94.305,"S"],[68.34,78.201,"S"],[69.65,105.745,"S"],[71.41,78.202,"S"]],"GRO":[[36.34,78.988,"S"],[37.65,96.603,"S"],[39.26,78.584,"S"],[40.57,100.218,"S"],[42.24,78.518,"S"],[43.55,100.986,"S"],[45.23,78.517,"S"],[46.54,101.319,"S"],[48.23,78.132,"S"],[64.96,78.454,"S"],[66.27,102.39,"S"],[67.98,78.484,"S"],[69.29,108.823,"S"],[71.1,78.666,"S"]],"HAM":[[25.08,77.916,"S"],[26.38,91.998,"S"],[27.92,76.931,"S"],[33.72,76.68,"S"],[47.15,77.389,"S"],[48.44,96.967,"S"],[50.06,105.599,"S"],[62.03,80.718,"S"],[63.37,80.849,"S"],[64.72,81.537,"S"],[66.08,80.841,"S"],[67.43,80.541,"S"],[68.77,80.84,"S"],[70.12,81.824,"S"],[71.48,80.877,"S"]],"KVY":[[25.73,79.726,"M"],[27.06,98.081,"M"],[28.69,78.501,"M"],[30.0,92.862,"M"],[31.55,78.148,"M"],[32.85,93.645,"M"],[34.41,77.968,"M"],[45.33,80.514,"M"],[46.67,81.422,"M"],[48.03,79.61,"M"],[49.36,79.777,"M"],[50.69,79.739,"M"],[52.02,79.616,"M"],[53.34,80.223,"M"],[54.68,81.438,"M"],[56.04,80.056,"M"],[57.37,80.514,"M"],[66.5,78.103,"S"],[67.8,93.976,"S"],[69.37,77.72,"S"],[70.66,89.592,"S"],[72.16,78.007,"S"]],"LAT":[[27.67,90.044,"M"],[29.17,80.11,"M"],[30.5,103.904,"M"],[32.23,79.464,"M"],[41.14,78.533,"S"],[42.45,99.035,"S"],[44.1,78.397,"S"],[62.52,87.772,"S"],[63.98,90.464,"S"],[65.49,78.636,"S"]],"LEC":[[26.83,89.919,"S"],[28.33,78.028,"S"],[29.63,111.088,"S"],[31.48,77.41,"S"],[32.77,108.818,"S"],[50.67,77.229,"S"],[51.96,110.104,"S"],[67.51,81.079,"S"],[68.87,81.255,"S"],[70.22,81.181,"S"],[71.57,80.946,"S"]],"MAG":[[36.55,78.794,"S"],[37.86,112.877,"S"],[39.75,78.373,"S"],[65.03,78.447,"S"],[66.34,112.056,"S"],[68.21,104.758,"S"],[69.95,85.338,"S"],[71.37,78.287,"S"]],"NOR":[[27.37,84.784,"M"],[28.79,78.751,"M"],[30.1,93.05,"M"],[31.65,77.935,"M"],[32.95,95.328,"M"],[34.54,77.7,"M"],[35.83,95.4,"M"],[52.63,85.175,"S"],[54.05,89.034,"S"],[55.54,77.755,"S"],[56.83,94.94,"S"],[58.41,77.478,"S"],[59.71,95.844,"S"],[61.3,81.538,"S"],[62.66,93.012,"S"]],"OCO":[[29.6,83.771,"M"],[31.0,79.049,"M"],[32.32,89.648,"M"],[33.81,78.298,"M"],[35.11,91.227,"M"],[36.64,77.891,"M"],[37.93,87.412,"M"],[39.39,77.666,"M"],[57.66,86.749,"S"],[59.1,77.856,"S"],[60.4,84.085,"S"],[61.8,78.129,"S"],[63.1,102.894,"S"],[64.82,89.636,"S"],[66.31,78.09,"S"]],"PER":[[38.95,84.422,"M"],[40.36,78.706,"M"],[41.67,91.192,"M"],[43.19,77.895,"M"],[44.49,93.366,"M"],[46.05,77.701,"M"],[47.34,93.151,"M"],[48.89,77.297,"M"],[66.71,82.333,"S"],[68.09,84.357,"S"],[69.49,77.621,"S"],[70.79,93.39,"S"],[72.34,77.395,"S"]],"RAI":[[28.46,79.45,"S"],[31.39,78.59,"S"],[32.7,97.956,"S"],[34.33,87.402,"S"],[35.79,78.577,"S"],[37.1,98.686,"S"],[38.74,78.09,"S"],[40.04,96.539,"S"],[41.65,77.922,"S"],[65.75,78.564,"S"],[67.06,89.354,"S"],[68.55,92.36,"S"],[70.08,97.21,"S"],[71.7,85.786,"S"]],"RIC":[[26.32,85.291,"M"],[27.75,78.831,"M"],[29.06,98.954,"M"],[30.71,77.935,"M"],[58.15,81.911,"S"],[59.52,78.451,"S"]],"RUS":[[34.11,79.311,"S"],[35.43,107.765,"S"],[37.23,78.647,"S"],[38.54,102.531,"S"],[40.24,78.032,"S"],[41.55,105.857,"S"],[51.7,78.144,"S"],[53.0,95.152,"S"],[54.59,78.143,"S"],[55.89,102.191,"S"],[57.59,78.171,"S"],[58.89,105.374,"S"],[60.65,78.098,"S"]],"SAI":[[29.69,85.963,"M"],[31.12,78.13,"M"],[32.43,90.037,"M"],[33.93,77.593,"M"],[35.22,92.977,"M"],[36.77,83.264,"M"],[38.16,77.57,"M"],[39.45,90.605,"M"],[40.96,77.242,"M"],[51.41,82.304,"S"],[52.78,77.545,"S"],[54.07,94.596,"S"],[55.65,77.238,"S"],[56.94,96.81,"S"],[58.55,85.355,"S"],[59.97,78.409,"S"],[61.28,90.627,"S"]],"STR":[[38.52,81.638,"M"],[39.89,78.999,"M"],[41.2,89.442,"M"],[42.69,78.464,"M"],[44.0,92.434,"M"],[45.54,78.278,"M"],[46.85,92.632,"M"],[48.39,78.159,"M"],[65.71,78.1,"S"],[67.02,89.836,"S"],[68.51,78.09,"S"],[69.81,103.4,"S"],[71.54,93.614,"S"]],"VER":[[34.21,82.111,"M"],[35.58,77.659,"M"],[36.87,89.694,"M"],[38.37,77.228,"M"],[39.65,94.807,"M"],[41.23,76.659,"M"],[42.51,87.33,"M"],[43.97,76.812,"M"],[59.6,82.519,"S"],[60.98,77.607,"S"],[62.27,99.232,"S"],[63.93,86.477,"S"],[65.37,77.25,"S"],[66.65,105.05,"S"],[68.41,77.188,"S"],[69.69,117.359,"S"],[71.65,94.937,"S"]],"VET":[[27.49,87.657,"S"],[28.95,78.859,"S"],[30.27,96.285,"S"],[31.87,89.617,"S"],[33.36,78.258,"S"],[34.67,94.442,"S"],[36.24,78.079,"S"],[50.52,77.73,"S"],[51.82,100.53,"S"],[53.49,77.911,"S"],[54.79,97.82,"S"],[56.42,77.685,"S"],[67.72,81.08,"S"],[69.08,80.987,"S"],[70.43,81.679,"S"],[71.79,81.715,"S"]]},"longRuns":[{"code":"KVY","c":"M","laps":10,"avg":80.291},{"code":"HAM","c":"S","laps":8,"avg":81.003},{"code":"GAS","c":"S","laps":7,"avg":81.174},{"code":"VER","c":"M","laps":8,"avg":82.787},{"code":"BOT","c":"S","laps":10,"avg":82.787},{"code":"OCO","c":"M","laps":8,"avg":83.12},{"code":"SAI","c":"M","laps":9,"avg":83.709},{"code":"STR","c":"M","laps":8,"avg":83.756},{"code":"PER","c":"M","laps":8,"avg":84.216},{"code":"OCO","c":"S","laps":7,"avg":85.348},{"code":"SAI","c":"S","laps":8,"avg":85.361},{"code":"KVY","c":"M","laps":7,"avg":85.562},{"code":"RAI","c":"S","laps":9,"avg":85.912},{"code":"ALB","c":"M","laps":9,"avg":86.109},{"code":"NOR","c":"M","laps":7,"avg":86.135},{"code":"VET","c":"S","laps":7,"avg":86.171},{"code":"GAS","c":"S","laps":6,"avg":86.757},{"code":"NOR","c":"S","laps":8,"avg":86.847},{"code":"RUS","c":"S","laps":7,"avg":87.896},{"code":"GRO","c":"S","laps":9,"avg":87.985},{"code":"ALB","c":"S","laps":10,"avg":90.289},{"code":"GIO","c":"S","laps":11,"avg":90.661},{"code":"VER","c":"S","laps":9,"avg":90.847},{"code":"RUS","c":"S","laps":6,"avg":92.024}],"speedTraps":[{"code":"OCO","st":328.0,"fl":310.0},{"code":"RUS","st":328.0,"fl":317.0},{"code":"BOT","st":328.0,"fl":312.0},{"code":"HAM","st":327.0,"fl":314.0},{"code":"LAT","st":326.0,"fl":308.0},{"code":"SAI","st":326.0,"fl":321.0},{"code":"RIC","st":325.0,"fl":307.0},{"code":"KVY","st":325.0,"fl":310.0},{"code":"VER","st":325.0,"fl":311.0},{"code":"NOR","st":324.0,"fl":306.0},{"code":"RAI","st":324.0,"fl":305.0},{"code":"STR","st":324.0,"fl":309.0},{"code":"GAS","st":323.0,"fl":309.0},{"code":"PER","st":323.0,"fl":312.0},{"code":"ALB","st":323.0,"fl":308.0},{"code":"GIO","st":323.0,"fl":311.0},{"code":"LEC","st":321.0,"fl":302.0},{"code":"GRO","st":319.0,"fl":303.0},{"code":"VET","st":317.0,"fl":321.0},{"code":"MAG","st":316.0,"fl":310.0}],"raceControl":[{"lap":null,"time":"10:00","cat":"Flag","flag":"GREEN","msg":"GREEN LIGHT - PIT EXIT OPEN"},{"lap":null,"time":"10:13","cat":"Other","flag":null,"msg":"TRACK SURFACE SLIPPERY IN TRACK SECTOR 10"},{"lap":null,"time":"10:13","cat":"Flag","flag":"CLEAR","msg":"CLEAR IN TRACK SECTOR 10"},{"lap":null,"time":"10:15","cat":"Other","flag":null,"msg":"CAR 6 (LAT) TIME 1:20.110 DELETED - TRACK LIMITS AT TURN 1"},{"lap":null,"time":"10:16","cat":"Other","flag":null,"msg":"CAR 55 (SAI) TIME 1:25.963 DELETED - TRACK LIMITS AT TURN 1"},{"lap":null,"time":"10:18","cat":"Other","flag":null,"msg":"CAR 7 (RAI) TIME 1:18.590 DELETED - TRACK LIMITS AT TURN 1"},{"lap":null,"time":"10:20","cat":"Flag","flag":"YELLOW","msg":"YELLOW IN TRACK SECTOR 16"},{"lap":null,"time":"10:20","cat":"Flag","flag":"CLEAR","msg":"CLEAR IN TRACK SECTOR 16"},{"lap":null,"time":"10:20","cat":"Other","flag":null,"msg":"CAR 63 (RUS) TIME 1:19.311 DELETED - TRACK LIMITS AT TURN 1"},{"lap":null,"time":"10:21","cat":"CarEvent","flag":null,"msg":"CAR 16 (LEC) SPUN AND CONTINUED AT TURN 14"},{"lap":null,"time":"10:21","cat":"Other","flag":null,"msg":"CAR 63 (RUS) TIME 1:19.311 DELETED - TRACK LIMITS AT TURN 1"},{"lap":null,"time":"10:24","cat":"Other","flag":null,"msg":"CAR 99 (GIO) TIME 1:18.371 DELETED - TRACK LIMITS AT TURN 1"},{"lap":null,"time":"10:26","cat":"Other","flag":null,"msg":"CAR 8 (GRO) TIME 1:18.584 DELETED - TRACK LIMITS AT TURN 1"},{"lap":null,"time":"10:27","cat":"Other","flag":null,"msg":"CAR 23 (ALB) TIME 1:17.179 DELETED - TRACK LIMITS AT TURN 1"},{"lap":null,"time":"10:27","cat":"Other","flag":null,"msg":"CAR 33 (VER) TIME 1:16.659 DELETED - TRACK LIMITS AT TURN 1"},{"lap":null,"time":"10:28","cat":"Flag","flag":"YELLOW","msg":"YELLOW IN TRACK SECTOR 6"},{"lap":null,"time":"10:28","cat":"Flag","flag":"CLEAR","msg":"CLEAR IN TRACK SECTOR 6"},{"lap":null,"time":"10:29","cat":"CarEvent","flag":null,"msg":"CAR 63 (RUS) OFF TRACK AND CONTINUED AT TURN 5"},{"lap":null,"time":"10:31","cat":"Other","flag":null,"msg":"CAR 8 (GRO) TIME 1:18.517 DELETED - TRACK LIMITS AT TURN 1"},{"lap":null,"time":"10:35","cat":"Other","flag":null,"msg":"CAR 10 (GAS) TIME 1:20.731 DELETED - TRACK LIMITS AT TURN 4"},{"lap":null,"time":"10:35","cat":"Other","flag":null,"msg":"CAR 23 (ALB) TIME 1:16.949 DELETED - TRACK LIMITS AT TURN 1"},{"lap":null,"time":"10:35","cat":"Flag","flag":"YELLOW","msg":"YELLOW IN TRACK SECTOR 10"},{"lap":null,"time":"10:35","cat":"Other","flag":null,"msg":"CAR 10 (GAS) TIME 1:20.301 DELETED - TRACK LIMITS AT TURN 1"},{"lap":null,"time":"10:35","cat":"Flag","flag":"CLEAR","msg":"CLEAR IN TRACK SECTOR 10"},{"lap":null,"time":"10:36","cat":"CarEvent","flag":null,"msg":"CAR 44 (HAM) OFF TRACK AND CONTINUED AT TURN 8"},{"lap":null,"time":"10:36","cat":"Other","flag":null,"msg":"CAR 8 (GRO) TIME 1:18.132 DELETED - TRACK LIMITS AT TURN 4"},{"lap":null,"time":"10:38","cat":"Other","flag":null,"msg":"CAR 26 (KVY) TIME 1:19.739 DELETED - TRACK LIMITS AT TURN 1"},{"lap":null,"time":"10:40","cat":"Other","flag":null,"msg":"CAR 4 (NOR) TIME 1:29.034 DELETED - TRACK LIMITS AT TURN 1"},{"lap":null,"time":"10:41","cat":"Other","flag":null,"msg":"CAR 26 (KVY) TIME 1:21.438 DELETED - TRACK LIMITS AT TURN 4"},{"lap":null,"time":"10:46","cat":"Other","flag":null,"msg":"CAR 77 (BOT) TIME 1:21.198 DELETED - TRACK LIMITS AT TURN 1"},{"lap":null,"time":"10:47","cat":"Other","flag":null,"msg":"CAR 55 (SAI) TIME 1:18.409 DELETED - TRACK LIMITS AT TURN 1"},{"lap":null,"time":"10:48","cat":"Other","flag":null,"msg":"CAR 31 (OCO) TIME 1:18.129 DELETED - TRACK LIMITS AT TURN 1"},{"lap":null,"time":"10:53","cat":"Other","flag":null,"msg":"CAR 10 (GAS) TIME 1:41.449 DELETED - TRACK LIMITS AT TURN 1"},{"lap":null,"time":"10:54","cat":"Other","flag":null,"msg":"CAR 8 (GRO) TIME 1:18.484 DELETED - TRACK LIMITS AT TURN 1"},{"lap":null,"time":"10:55","cat":"Other","flag":null,"msg":"CAR 18 (STR) TIME 1:18.090 DELETED - TRACK LIMITS AT TURN 1"},{"lap":null,"time":"10:55","cat":"Other","flag":null,"msg":"CAR 20 (MAG) TIME 1:44.758 DELETED - TRACK LIMITS AT TURN 1"},{"lap":null,"time":"10:58","cat":"Other","flag":null,"msg":"CAR 8 (GRO) TIME 1:18.666 DELETED - TRACK LIMITS AT TURN 1"},{"lap":null,"time":"10:58","cat":"Flag","flag":"RED","msg":"RED FLAG"},{"lap":null,"time":"10:59","cat":"Other","flag":null,"msg":"SESSION WILL NOT BE RESTARTED"},{"lap":null,"time":"11:03","cat":"Flag","flag":"CLEAR","msg":"TRACK CLEAR"}]}
