{"schema":1,"type":"practice","session":"fp3","drivers":[{"code":"RIC","ref":"ricciardo","name":"Daniel Ricciardo","team":"McLaren","teamId":"mclaren","color":"#FF8000","position":null,"grid":null,"status":null,"gap":null,"points":null},{"code":"NOR","ref":"norris","name":"Lando Norris","team":"McLaren","teamId":"mclaren","color":"#FF8000","position":null,"grid":null,"status":null,"gap":null,"points":null},{"code":"VET","ref":"vettel","name":"Sebastian Vettel","team":"Aston Martin","teamId":"aston","color":"#229971","position":null,"grid":null,"status":null,"gap":null,"points":null},{"code":"LAT","ref":"latifi","name":"Nicholas Latifi","team":"Williams","teamId":"williams","color":"#64C4FF","position":null,"grid":null,"status":null,"gap":null,"points":null},{"code":"RAI","ref":"raikkonen","name":"Kimi Räikkönen","team":"Alfa Romeo Racing","teamId":"alfa","color":"#888888","position":null,"grid":null,"status":null,"gap":null,"points":null},{"code":"MAZ","ref":"mazepin","name":"Nikita Mazepin","team":"Haas F1 Team","teamId":"haas","color":"#B6BABD","position":null,"grid":null,"status":null,"gap":null,"points":null},{"code":"GAS","ref":"gasly","name":"Pierre Gasly","team":"AlphaTauri","teamId":"alphatauri","color":"#888888","position":null,"grid":null,"status":null,"gap":null,"points":null},{"code":"PER","ref":"perez","name":"Sergio Perez","team":"Red Bull Racing","teamId":"redbull","color":"#3671C6","position":null,"grid":null,"status":null,"gap":null,"points":null},{"code":"ALO","ref":"alonso","name":"Fernando Alonso","team":"Alpine","teamId":"alpine","color":"#0093CC","position":null,"grid":null,"status":null,"gap":null,"points":null},{"code":"LEC","ref":"leclerc","name":"Charles Leclerc","team":"Ferrari","teamId":"ferrari","color":"#E80020","position":null,"grid":null,"status":null,"gap":null,"points":null},{"code":"STR","ref":"stroll","name":"Lance Stroll","team":"Aston Martin","teamId":"aston","color":"#229971","position":null,"grid":null,"status":null,"gap":null,"points":null},{"code":"TSU","ref":"tsunoda","name":"Yuki Tsunoda","team":"AlphaTauri","teamId":"alphatauri","color":"#888888","position":null,"grid":null,"status":null,"gap":null,"points":null},{"code":"OCO","ref":"ocon","name":"Esteban Ocon","team":"Alpine","teamId":"alpine","color":"#0093CC","position":null,"grid":null,"status":null,"gap":null,"points":null},{"code":"VER","ref":"max_verstappen","name":"Max Verstappen","team":"Red Bull Racing","teamId":"redbull","color":"#3671C6","position":null,"grid":null,"status":null,"gap":null,"points":null},{"code":"HAM","ref":"hamilton","name":"Lewis Hamilton","team":"Mercedes","teamId":"mercedes","color":"#27F4D2","position":null,"grid":null,"status":null,"gap":null,"points":null},{"code":"MSC","ref":"mick_schumacher","name":"Mick Schumacher","team":"Haas F1 Team","teamId":"haas","color":"#B6BABD","position":null,"grid":null,"status":null,"gap":null,"points":null},{"code":"SAI","ref":"sainz","name":"Carlos Sainz","team":"Ferrari","teamId":"ferrari","color":"#E80020","position":null,"grid":null,"status":null,"gap":null,"points":null},{"code":"RUS","ref":"russell","name":"George Russell","team":"Williams","teamId":"williams","color":"#64C4FF","position":null,"grid":null,"status":null,"gap":null,"points":null},{"code":"BOT","ref":"bottas","name":"Valtteri Bottas","team":"Mercedes","teamId":"mercedes","color":"#27F4D2","position":null,"grid":null,"status":null,"gap":null,"points":null},{"code":"GIO","ref":"giovinazzi","name":"Antonio Giovinazzi","team":"Alfa Romeo Racing","teamId":"alfa","color":"#888888","position":null,"grid":null,"status":null,"gap":null,"points":null}],"weather":{"airMin":18.0,"airMax":19.4,"trackMin":26.9,"trackMax":31.2,"windAvg":0.682,"windDirDeg":173,"rain":false,"samples":[[0.3,18.3,27.7,1.44,0],[1.3,18.3,27.7,0.36,0],[2.3,18.3,27.8,0.36,0],[3.3,18.3,27.8,0.36,0],[4.3,18.3,27.2,0.0,0],[5.3,18.2,27.2,0.36,0],[6.3,18.2,27.7,0.36,0],[7.3,18.2,27.7,0.0,0],[8.3,18.1,27.4,0.0,0],[9.3,18.0,27.5,0.0,0],[10.3,18.1,27.7,0.36,0],[11.3,18.2,27.8,0.36,0],[12.3,18.2,27.8,0.36,0],[13.3,18.1,27.6,0.72,0],[14.3,18.1,27.7,0.36,0],[15.3,18.0,27.6,0.0,0],[16.3,18.1,27.7,0.36,0],[17.3,18.0,27.8,1.8,0],[18.3,18.0,27.6,0.36,0],[19.3,18.2,27.4,0.0,0],[20.3,18.2,27.7,0.36,0],[21.3,18.1,27.7,0.36,0],[22.3,18.1,27.5,0.0,0],[23.3,18.2,27.9,0.36,0],[24.3,18.2,27.9,0.72,0],[25.3,18.3,27.9,0.36,0],[26.3,18.3,27.5,0.36,0],[27.3,18.2,27.2,0.0,0],[28.3,18.1,26.9,0.36,0],[29.3,18.2,27.2,0.0,0],[30.3,18.3,27.4,1.08,0],[31.3,18.5,27.6,0.72,0],[32.3,18.5,27.0,0.72,0],[33.3,18.4,27.0,0.72,0],[34.3,18.4,27.0,1.08,0],[35.3,18.5,27.2,0.36,0],[36.3,18.5,27.3,0.72,0],[37.3,18.6,27.4,0.36,0],[38.3,18.7,27.7,1.08,0],[39.3,18.8,27.8,1.8,0],[40.3,18.8,27.9,1.8,0],[41.3,18.6,28.4,1.08,0],[42.3,18.6,28.5,0.36,0],[43.3,18.6,29.1,0.36,0],[44.3,18.6,29.1,1.08,0],[45.3,18.7,29.4,1.08,0],[46.3,18.7,30.0,0.72,0],[47.3,18.9,30.0,0.36,0],[48.3,19.1,29.8,0.36,0],[49.3,19.1,29.8,0.36,0],[50.3,19.0,29.9,0.72,0],[51.3,18.9,29.5,0.72,0],[52.3,18.8,29.5,0.72,0],[53.3,18.7,29.5,0.36,0],[54.3,18.7,29.5,0.72,0],[55.3,18.5,29.5,0.72,0],[56.3,18.4,29.0,1.08,0],[57.3,18.5,28.9,1.08,0],[58.3,18.4,28.6,0.72,0],[59.3,18.4,28.7,0.72,0],[60.3,18.4,28.7,1.08,0],[61.3,18.4,28.7,1.08,0],[62.3,18.4,29.0,0.72,0],[63.3,18.5,29.3,1.08,0],[64.3,18.6,30.0,1.44,0],[65.3,18.6,30.1,1.08,0],[66.3,18.7,31.0,0.72,0],[67.3,18.9,31.0,1.08,0],[68.3,18.9,30.4,1.08,0],[69.3,18.9,30.9,1.08,0],[70.3,19.1,31.1,1.08,0],[71.3,19.3,31.1,1.08,0],[72.3,19.3,31.2,1.8,0],[73.3,19.4,30.6,0.72,0],[74.3,19.3,30.6,1.44,0],[75.3,19.1,30.2,0.72,0]]},"order":[{"code":"VER","t":71.294},{"code":"SAI","t":71.341},{"code":"LEC","t":71.552},{"code":"BOT","t":71.765},{"code":"PER","t":71.817},{"code":"NOR","t":71.988},{"code":"HAM","t":72.02},{"code":"RAI","t":72.298},{"code":"GAS","t":72.357},{"code":"VET","t":72.537},{"code":"GIO","t":72.539},{"code":"STR","t":72.7},{"code":"RIC","t":72.959},{"code":"MSC","t":73.139},{"code":"ALO","t":73.329},{"code":"MAZ","t":73.39},{"code":"RUS","t":73.447},{"code":"LAT","t":73.475},{"code":"TSU","t":73.522},{"code":"OCO","t":73.614}],"lapsAll":{"ALO":[[25.43,74.592,"S"],[26.68,85.342,"S"],[28.1,73.76,"S"],[29.33,90.942,"S"],[30.85,78.255,"S"],[43.08,73.329,"S"],[44.31,90.287,"S"],[45.81,73.362,"S"],[64.84,73.469,"S"],[66.06,88.349,"S"],[67.53,81.388,"S"],[68.89,73.339,"S"],[70.11,108.386,"S"]],"BOT":[[32.51,81.309,"S"],[33.87,72.37,"S"],[35.07,85.269,"S"],[36.49,76.753,"S"],[37.77,72.36,"S"],[38.98,95.873,"S"],[40.58,72.084,"S"],[41.78,86.807,"S"],[43.23,80.93,"S"],[44.57,77.571,"S"],[65.43,80.259,"S"],[66.76,72.054,"S"],[67.96,91.487,"S"],[69.49,71.765,"S"],[70.69,93.381,"S"]],"GAS":[[24.66,76.279,"M"],[25.93,79.502,"M"],[27.26,86.47,"M"],[28.7,80.739,"M"],[30.04,73.563,"M"],[31.27,96.923,"M"],[32.89,73.012,"M"],[34.1,92.91,"M"],[35.65,72.626,"M"],[36.86,94.8,"M"],[38.44,73.152,"M"],[39.66,95.565,"M"],[41.25,72.771,"M"],[53.13,78.316,"S"],[54.44,72.749,"S"],[55.65,90.907,"S"],[65.48,85.112,"S"],[66.9,72.916,"S"],[68.12,98.742,"S"],[69.76,72.357,"S"],[70.97,87.41,"S"]],"GIO":[[20.1,76.087,"S"],[21.37,88.527,"S"],[22.85,73.946,"S"],[24.08,96.538,"S"],[25.69,73.266,"S"],[26.91,85.927,"S"],[28.34,72.563,"S"],[29.55,91.527,"S"],[31.08,72.721,"S"],[52.15,73.331,"S"],[53.37,93.321,"S"],[54.93,72.539,"S"],[67.26,72.877,"S"],[68.47,97.065,"S"],[70.09,72.71,"S"]],"HAM":[[32.0,80.801,"S"],[33.35,73.278,"S"],[34.57,84.941,"S"],[35.99,72.239,"S"],[37.19,84.931,"S"],[38.61,72.02,"S"],[39.81,97.226,"S"],[41.43,77.135,"S"],[64.69,81.118,"S"],[66.04,80.469,"S"],[67.38,82.618,"S"],[68.76,85.974,"S"],[70.19,77.089,"S"],[71.48,77.382,"S"]],"LAT":[[24.85,78.522,"M"],[26.16,80.039,"M"],[27.49,74.695,"M"],[28.74,97.941,"M"],[30.37,86.291,"M"],[31.81,73.742,"M"],[33.04,91.419,"M"],[34.56,76.356,"M"],[35.83,75.273,"M"],[37.09,75.559,"M"],[38.35,75.325,"M"],[39.6,75.66,"M"],[40.86,75.895,"M"],[42.13,75.912,"M"],[50.72,73.475,"S"],[51.94,92.915,"S"],[53.49,73.8,"S"],[54.72,93.428,"S"]],"LEC":[[23.74,82.371,"S"],[25.11,72.633,"S"],[26.32,92.164,"S"],[27.86,72.223,"S"],[29.06,102.466,"S"],[30.77,71.658,"S"],[31.96,103.586,"S"],[33.69,71.785,"S"],[34.89,92.538,"S"],[36.43,73.222,"S"],[37.65,109.472,"S"],[39.47,71.696,"S"],[40.67,97.184,"S"],[42.29,71.739,"S"],[53.04,93.346,"S"],[54.59,110.264,"S"],[67.02,71.552,"S"],[68.21,71.6,"S"],[69.4,103.13,"S"]],"MAZ":[[22.07,82.971,"H"],[23.45,78.857,"H"],[24.76,80.369,"H"],[38.68,75.213,"S"],[39.94,94.062,"S"],[41.5,73.851,"S"],[42.74,93.181,"S"],[44.29,73.39,"S"],[45.51,98.964,"S"],[65.06,76.4,"S"],[66.33,84.9,"S"],[67.75,73.844,"S"],[68.98,101.993,"S"],[70.68,85.437,"S"]],"MSC":[[22.52,81.97,"H"],[23.88,78.635,"H"],[25.19,76.955,"H"],[38.93,74.949,"S"],[40.18,103.858,"S"],[41.91,74.813,"S"],[43.16,97.35,"S"],[44.78,74.219,"S"],[46.02,90.992,"S"],[47.53,73.799,"S"],[65.2,96.469,"S"],[66.81,74.075,"S"],[68.04,92.262,"S"],[69.58,73.139,"S"],[70.8,90.862,"S"]],"NOR":[[24.74,74.211,"S"],[25.98,104.168,"S"],[27.72,73.155,"S"],[28.94,93.959,"S"],[30.5,72.603,"S"],[31.71,94.648,"S"],[33.29,81.661,"S"],[34.65,89.989,"S"],[36.15,72.28,"S"],[37.35,88.172,"S"],[53.29,73.072,"S"],[54.5,89.266,"S"],[55.99,71.988,"S"]],"OCO":[[30.94,76.133,"S"],[32.21,93.901,"S"],[33.77,74.331,"S"],[35.01,97.504,"S"],[36.64,73.867,"S"],[37.87,90.87,"S"],[39.38,73.614,"S"],[40.61,84.692,"S"],[42.02,73.869,"S"],[64.63,74.645,"S"],[65.87,96.101,"S"],[67.47,73.709,"S"],[68.7,94.809,"S"],[70.28,92.56,"S"]],"PER":[[27.24,74.994,"M"],[28.49,88.742,"M"],[29.97,72.924,"M"],[31.19,91.434,"M"],[32.71,72.367,"M"],[33.92,97.574,"M"],[35.54,72.135,"M"],[36.74,106.673,"M"],[38.52,72.189,"M"],[65.55,91.201,"S"],[67.07,71.822,"S"],[68.27,100.399,"S"],[69.94,71.817,"S"]],"RAI":[[19.47,84.937,"S"],[20.89,74.293,"S"],[22.13,90.766,"S"],[23.64,73.432,"S"],[24.87,86.254,"S"],[26.3,75.068,"S"],[27.55,87.867,"S"],[29.02,73.202,"S"],[30.24,98.329,"S"],[31.88,72.966,"S"],[51.09,72.46,"S"],[52.3,95.726,"S"],[53.89,72.298,"S"],[55.1,98.068,"S"],[66.3,76.258,"S"],[67.57,83.522,"S"],[68.96,82.002,"S"],[70.33,79.267,"S"],[71.65,73.944,"S"]],"RIC":[[21.74,74.792,"S"],[22.99,89.143,"S"],[24.48,74.151,"S"],[25.71,97.475,"S"],[27.34,73.58,"S"],[28.56,104.085,"S"],[30.3,73.436,"S"],[31.52,86.177,"S"],[32.96,73.218,"S"],[34.18,91.491,"S"],[35.7,81.428,"S"],[50.58,76.77,"S"],[51.86,73.393,"S"],[53.08,94.552,"S"],[54.66,84.78,"S"],[56.07,72.959,"S"],[68.93,79.081,"S"],[70.25,78.708,"S"],[71.56,77.883,"S"]],"RUS":[[22.98,82.21,"M"],[24.35,76.881,"M"],[25.63,95.581,"M"],[27.22,75.277,"M"],[28.48,104.537,"M"],[30.22,74.554,"M"],[31.46,78.784,"M"],[32.77,75.272,"M"],[34.03,75.539,"M"],[35.29,74.81,"M"],[36.54,75.578,"M"],[37.79,76.664,"M"],[50.05,80.846,"S"],[51.39,73.695,"S"],[52.62,100.028,"S"],[54.29,73.545,"S"],[55.51,91.583,"S"],[65.36,80.282,"S"],[66.7,73.447,"S"],[67.92,87.631,"S"],[69.38,73.539,"S"]],"SAI":[[22.92,80.22,"S"],[24.26,73.3,"S"],[25.48,100.061,"S"],[27.15,72.533,"S"],[28.36,106.464,"S"],[30.13,78.741,"S"],[31.44,72.183,"S"],[32.65,112.623,"S"],[34.52,71.847,"S"],[35.72,108.681,"S"],[37.53,71.905,"S"],[38.73,102.668,"S"],[40.44,71.452,"S"],[51.26,88.718,"S"],[52.74,71.659,"S"],[53.93,92.94,"S"],[55.48,71.341,"S"],[67.14,77.882,"S"],[68.44,71.363,"S"],[69.63,99.397,"S"],[71.29,74.134,"S"]],"STR":[[26.39,75.131,"S"],[27.65,91.803,"S"],[29.18,73.564,"S"],[30.4,99.945,"S"],[32.07,89.842,"S"],[33.57,72.843,"S"],[34.78,95.84,"S"],[36.38,72.867,"S"],[37.59,100.819,"S"],[39.27,72.729,"S"],[52.93,73.009,"S"],[54.15,102.153,"S"],[55.85,72.7,"S"],[67.29,91.887,"S"],[68.82,74.178,"S"],[70.05,100.128,"S"]],"TSU":[[22.01,78.44,"S"],[23.31,76.321,"S"],[24.59,74.727,"S"],[25.83,74.608,"S"],[27.08,83.001,"S"],[28.46,87.352,"S"],[29.91,74.407,"S"],[31.16,88.704,"S"],[32.63,74.098,"S"],[33.87,95.801,"S"],[35.47,74.179,"S"],[36.7,94.442,"S"],[38.28,73.55,"S"],[39.5,100.592,"S"],[41.18,73.522,"S"],[42.4,90.941,"S"],[43.92,73.537,"S"],[53.57,74.001,"S"],[54.8,102.543,"S"],[64.55,82.316,"S"],[65.93,75.108,"S"],[67.18,86.279,"S"],[68.62,83.898,"S"],[70.01,84.308,"S"]],"VER":[[28.19,73.36,"S"],[29.41,95.675,"S"],[31.01,72.495,"S"],[32.22,104.146,"S"],[33.95,71.759,"S"],[35.15,101.043,"S"],[36.83,71.485,"S"],[38.02,97.12,"S"],[39.64,87.565,"S"],[64.47,71.504,"S"],[65.66,92.252,"S"],[67.2,78.89,"S"],[68.51,71.294,"S"],[69.7,99.206,"S"],[71.35,71.309,"S"]],"VET":[[26.63,75.145,"S"],[27.88,85.213,"S"],[29.3,73.724,"S"],[30.53,100.447,"S"],[32.2,73.73,"S"],[33.43,107.254,"S"],[35.22,73.653,"S"],[36.44,98.227,"S"],[38.08,73.077,"S"],[39.3,91.57,"S"],[40.83,72.885,"S"],[53.35,85.78,"S"],[54.78,95.322,"S"],[65.28,79.252,"S"],[66.6,72.537,"S"],[67.81,83.136,"S"],[69.19,79.62,"S"],[70.52,74.784,"S"]]},"longRuns":[{"code":"LAT","c":"M","laps":14,"avg":79.473},{"code":"BOT","c":"S","laps":10,"avg":80.133},{"code":"HAM","c":"S","laps":8,"avg":80.321},{"code":"RUS","c":"M","laps":12,"avg":80.474},{"code":"VER","c":"S","laps":6,"avg":80.742},{"code":"HAM","c":"S","laps":6,"avg":80.775},{"code":"GIO","c":"S","laps":9,"avg":81.234},{"code":"TSU","c":"S","laps":17,"avg":81.66},{"code":"RAI","c":"S","laps":10,"avg":81.711},{"code":"OCO","c":"S","laps":9,"avg":82.087},{"code":"GAS","c":"M","laps":13,"avg":82.178},{"code":"PER","c":"M","laps":9,"avg":83.226},{"code":"RIC","c":"S","laps":11,"avg":83.543},{"code":"VET","c":"S","laps":11,"avg":84.084},{"code":"MSC","c":"S","laps":7,"avg":84.283},{"code":"NOR","c":"S","laps":10,"avg":84.485},{"code":"STR","c":"S","laps":10,"avg":84.538},{"code":"LEC","c":"S","laps":14,"avg":84.624},{"code":"MAZ","c":"S","laps":6,"avg":84.777},{"code":"VER","c":"S","laps":9,"avg":86.072},{"code":"SAI","c":"S","laps":13,"avg":86.36}],"speedTraps":[{"code":"RAI","st":283.0,"fl":273.0},{"code":"TSU","st":283.0,"fl":272.0},{"code":"RIC","st":282.0,"fl":270.0},{"code":"ALO","st":282.0,"fl":269.0},{"code":"HAM","st":282.0,"fl":268.0},{"code":"GIO","st":282.0,"fl":271.0},{"code":"LAT","st":281.0,"fl":270.0},{"code":"GAS","st":281.0,"fl":272.0},{"code":"PER","st":281.0,"fl":270.0},{"code":"LEC","st":281.0,"fl":270.0},{"code":"NOR","st":280.0,"fl":270.0},{"code":"VET","st":280.0,"fl":270.0},{"code":"MAZ","st":280.0,"fl":273.0},{"code":"VER","st":280.0,"fl":272.0},{"code":"SAI","st":280.0,"fl":271.0},{"code":"RUS","st":280.0,"fl":269.0},{"code":"BOT","st":280.0,"fl":271.0},{"code":"STR","st":279.0,"fl":269.0},{"code":"MSC","st":279.0,"fl":269.0},{"code":"OCO","st":276.0,"fl":268.0}],"raceControl":[{"lap":null,"time":"09:00","cat":"Other","flag":null,"msg":"AIR TEMPERATURE 1 HOUR BEFORE P3 = 18 DEGREES"},{"lap":null,"time":"09:45","cat":"Other","flag":null,"msg":"RISK OF RAIN FOR F1 THIRD PRACTICE SESSION IS 40%"},{"lap":null,"time":"10:02","cat":"Other","flag":null,"msg":"PIT EXIT IS OPEN"},{"lap":null,"time":"10:12","cat":"Other","flag":null,"msg":"CAR 6 (LAT) TIME 1:20.039 DELETED - TRACK LIMITS AT TURN 10"},{"lap":null,"time":"10:12","cat":"Other","flag":null,"msg":"CAR 16 (LEC) TIME 1:32.164 DELETED - TRACK LIMITS AT TURN 10"},{"lap":null,"time":"10:14","cat":"Other","flag":null,"msg":"CAR 7 (RAI) TIME 1:27.867 DELETED - TRACK LIMITS AT TURN 10"},{"lap":null,"time":"10:15","cat":"Other","flag":null,"msg":"CAR 55 (SAI) TIME 1:46.464 DELETED - TRACK LIMITS AT TURN 10"},{"lap":null,"time":"10:15","cat":"Other","flag":null,"msg":"CAR 63 (RUS) TIME 1:44.537 DELETED - TRACK LIMITS AT TURN 10"},{"lap":null,"time":"10:16","cat":"Other","flag":null,"msg":"CAR 55 (SAI) TIME 1:18.741 DELETED - TRACK LIMITS AT TURN 10"},{"lap":null,"time":"10:16","cat":"Other","flag":null,"msg":"CAR 7 (RAI) TIME 1:38.329 DELETED - TRACK LIMITS AT TURN 10"},{"lap":null,"time":"10:18","cat":"Other","flag":null,"msg":"CAR 3 (RIC) TIME 1:26.177 DELETED - TRACK LIMITS AT TURN 10"},{"lap":null,"time":"10:20","cat":"Other","flag":null,"msg":"CAR 5 (VET) TIME 1:47.254 DELETED - TRACK LIMITS AT TURN 10"},{"lap":null,"time":"10:21","cat":"Other","flag":null,"msg":"CAR 3 (RIC) TIME 1:31.491 DELETED - TRACK LIMITS AT TURN 10"},{"lap":null,"time":"10:23","cat":"Other","flag":null,"msg":"CAR 16 (LEC) TIME 1:32.538 DELETED - TRACK LIMITS AT TURN 10"},{"lap":null,"time":"10:23","cat":"Other","flag":null,"msg":"CAR 77 (BOT) TIME 1:25.269 DELETED - TRACK LIMITS AT TURN 10"},{"lap":null,"time":"10:23","cat":"Other","flag":null,"msg":"CAR 11 (PER) TIME 1:46.673 DELETED - TRACK LIMITS AT TURN 10"},{"lap":null,"time":"10:23","cat":"Other","flag":null,"msg":"CAR 44 (HAM) TIME 1:24.931 DELETED - TRACK LIMITS AT TURN 10"},{"lap":null,"time":"10:24","cat":"Other","flag":null,"msg":"CAR 33 (VER) TIME 1:37.120 DELETED - TRACK LIMITS AT TURN 10"},{"lap":null,"time":"10:25","cat":"Other","flag":null,"msg":"CAR 5 (VET) TIME 1:31.570 DELETED - TRACK LIMITS AT TURN 10"},{"lap":null,"time":"10:27","cat":"Other","flag":null,"msg":"CAR 16 (LEC) TIME 1:37.184 DELETED - TRACK LIMITS AT TURN 10"},{"lap":null,"time":"10:37","cat":"Other","flag":null,"msg":"CAR 3 (RIC) TIME 1:16.770 DELETED - TRACK LIMITS AT TURN 10"},{"lap":null,"time":"10:37","cat":"Other","flag":null,"msg":"CAR 55 (SAI) TIME 1:28.718 DELETED - TRACK LIMITS AT TURN 10"},{"lap":null,"time":"10:39","cat":"Other","flag":null,"msg":"CAR 16 (LEC) TIME 1:33.346 DELETED - TRACK LIMITS AT TURN 10"},{"lap":null,"time":"10:39","cat":"Other","flag":null,"msg":"DRS DISABLED IN ZONE 1"},{"lap":null,"time":"10:39","cat":"Other","flag":null,"msg":"DRS ENABLED IN ZONE 1"},{"lap":null,"time":"10:40","cat":"Other","flag":null,"msg":"CAR 3 (RIC) TIME 1:34.552 DELETED - TRACK LIMITS AT TURN 10"},{"lap":null,"time":"10:40","cat":"CarEvent","flag":null,"msg":"CAR 16 (LEC) OFF TRACK AND CONTINUED AT TURN 1"},{"lap":null,"time":"10:41","cat":"Flag","flag":"YELLOW","msg":"YELLOW IN TRACK SECTOR 2"},{"lap":null,"time":"10:41","cat":"Other","flag":null,"msg":"DRS DISABLED IN ZONE 1"},{"lap":null,"time":"10:41","cat":"Flag","flag":"CLEAR","msg":"CLEAR IN TRACK SECTOR 2"},{"lap":null,"time":"10:41","cat":"Other","flag":null,"msg":"DRS ENABLED IN ZONE 1"},{"lap":null,"time":"10:42","cat":"CarEvent","flag":null,"msg":"CAR 77 (BOT) OFF TRACK AND CONTINUED AT TURN 1"},{"lap":null,"time":"10:42","cat":"Flag","flag":"YELLOW","msg":"YELLOW IN TRACK SECTOR 16"},{"lap":null,"time":"10:42","cat":"Flag","flag":"DOUBLE YELLOW","msg":"DOUBLE YELLOW IN TRACK SECTOR 16"},{"lap":null,"time":"10:42","cat":"Flag","flag":"RED","msg":"RED FLAG"},{"lap":null,"time":"10:42","cat":"Flag","flag":"CLEAR","msg":"CLEAR IN TRACK SECTOR 16"},{"lap":null,"time":"10:42","cat":"Other","flag":null,"msg":"CAR 63 (RUS) TIME 1:31.583 DELETED - TRACK LIMITS AT TURN 10"},{"lap":null,"time":"10:42","cat":"CarEvent","flag":null,"msg":"CAR 55 (SAI) MISSED THE APEX OF TURN 1"},{"lap":null,"time":"10:43","cat":"Other","flag":null,"msg":"MEDICAL CAR DEPLOYED"},{"lap":null,"time":"10:46","cat":"Other","flag":null,"msg":"SESSION WILL RE-START AT 12:48"},{"lap":null,"time":"10:47","cat":"Flag","flag":"CLEAR","msg":"TRACK CLEAR"},{"lap":null,"time":"10:47","cat":"Drs","flag":null,"msg":"DRS ENABLED"},{"lap":null,"time":"10:48","cat":"Flag","flag":"GREEN","msg":"GREEN LIGHT - PIT EXIT OPEN"},{"lap":null,"time":"10:51","cat":"Other","flag":null,"msg":"CAR 9 (MAZ) TIME 1:16.400 DELETED - TRACK LIMITS AT TURN 10"},{"lap":null,"time":"10:53","cat":"Other","flag":null,"msg":"CAR 33 (VER) TIME 1:18.890 DELETED - TRACK LIMITS AT TURN 10"},{"lap":null,"time":"10:53","cat":"Other","flag":null,"msg":"CAR 44 (HAM) TIME 1:22.618 DELETED - TRACK LIMITS AT TURN 10"},{"lap":null,"time":"10:55","cat":"Other","flag":null,"msg":"CAR 31 (OCO) TIME 1:34.809 DELETED - TRACK LIMITS AT TURN 10"},{"lap":null,"time":"10:56","cat":"Other","flag":null,"msg":"CAR 16 (LEC) TIME 1:43.130 DELETED - TRACK LIMITS AT TURN 10"},{"lap":null,"time":"10:56","cat":"Other","flag":null,"msg":"CAR 55 (SAI) TIME 1:39.397 DELETED - TRACK LIMITS AT TURN 10"},{"lap":null,"time":"10:56","cat":"Other","flag":null,"msg":"CAR 33 (VER) TIME 1:39.206 DELETED - TRACK LIMITS AT TURN 10"},{"lap":null,"time":"10:56","cat":"Other","flag":null,"msg":"CAR 44 (HAM) TIME 1:17.089 DELETED - TRACK LIMITS AT TURN 10"},{"lap":null,"time":"10:56","cat":"Other","flag":null,"msg":"CAR 3 (RIC) TIME 1:18.708 DELETED - TRACK LIMITS AT TURN 10"},{"lap":null,"time":"10:56","cat":"Other","flag":null,"msg":"CAR 18 (STR) TIME 1:40.128 DELETED - TRACK LIMITS AT TURN 10"},{"lap":null,"time":"10:57","cat":"Flag","flag":"DOUBLE YELLOW","msg":"DOUBLE YELLOW IN TRACK SECTOR 6"},{"lap":null,"time":"10:57","cat":"Flag","flag":"RED","msg":"RED FLAG"},{"lap":null,"time":"10:57","cat":"Flag","flag":"CLEAR","msg":"CLEAR IN TRACK SECTOR 6"},{"lap":null,"time":"10:58","cat":"Other","flag":null,"msg":"MEDICAL CAR DEPLOYED"},{"lap":null,"time":"10:58","cat":"Other","flag":null,"msg":"SESSION WILL NOT BE RESTARTED"},{"lap":null,"time":"11:02","cat":"Flag","flag":"CLEAR","msg":"TRACK CLEAR"},{"lap":null,"time":"11:02","cat":"Drs","flag":null,"msg":"DRS ENABLED"},{"lap":null,"time":"11:02","cat":"Flag","flag":"DOUBLE YELLOW","msg":"DOUBLE YELLOW IN TRACK SECTOR 16"}]}
