{"schema":1,"type":"quali","session":"q","drivers":[{"code":"LEC","ref":"leclerc","name":"Charles Leclerc","team":"Ferrari","teamId":"ferrari","color":"#E80020","position":1,"grid":null,"status":null,"gap":null,"points":null},{"code":"HAM","ref":"hamilton","name":"Lewis Hamilton","team":"Mercedes","teamId":"mercedes","color":"#27F4D2","position":2,"grid":null,"status":null,"gap":null,"points":null},{"code":"VER","ref":"max_verstappen","name":"Max Verstappen","team":"Red Bull Racing","teamId":"redbull","color":"#3671C6","position":3,"grid":null,"status":null,"gap":null,"points":null},{"code":"GAS","ref":"gasly","name":"Pierre Gasly","team":"AlphaTauri","teamId":"alphatauri","color":"#888888","position":4,"grid":null,"status":null,"gap":null,"points":null},{"code":"SAI","ref":"sainz","name":"Carlos Sainz","team":"Ferrari","teamId":"ferrari","color":"#E80020","position":5,"grid":null,"status":null,"gap":null,"points":null},{"code":"NOR","ref":"norris","name":"Lando Norris","team":"McLaren","teamId":"mclaren","color":"#FF8000","position":6,"grid":null,"status":null,"gap":null,"points":null},{"code":"PER","ref":"perez","name":"Sergio Perez","team":"Red Bull Racing","teamId":"redbull","color":"#3671C6","position":7,"grid":null,"status":null,"gap":null,"points":null},{"code":"TSU","ref":"tsunoda","name":"Yuki Tsunoda","team":"AlphaTauri","teamId":"alphatauri","color":"#888888","position":8,"grid":null,"status":null,"gap":null,"points":null},{"code":"ALO","ref":"alonso","name":"Fernando Alonso","team":"Alpine","teamId":"alpine","color":"#0093CC","position":9,"grid":null,"status":null,"gap":null,"points":null},{"code":"BOT","ref":"bottas","name":"Valtteri Bottas","team":"Mercedes","teamId":"mercedes","color":"#27F4D2","position":10,"grid":null,"status":null,"gap":null,"points":null},{"code":"VET","ref":"vettel","name":"Sebastian Vettel","team":"Aston Martin","teamId":"aston","color":"#229971","position":11,"grid":null,"status":null,"gap":null,"points":null},{"code":"OCO","ref":"ocon","name":"Esteban Ocon","team":"Alpine","teamId":"alpine","color":"#0093CC","position":12,"grid":null,"status":null,"gap":null,"points":null},{"code":"RIC","ref":"ricciardo","name":"Daniel Ricciardo","team":"McLaren","teamId":"mclaren","color":"#FF8000","position":13,"grid":null,"status":null,"gap":null,"points":null},{"code":"RAI","ref":"raikkonen","name":"Kimi Räikkönen","team":"Alfa Romeo Racing","teamId":"alfa","color":"#888888","position":14,"grid":null,"status":null,"gap":null,"points":null},{"code":"RUS","ref":"russell","name":"George Russell","team":"Williams","teamId":"williams","color":"#64C4FF","position":15,"grid":null,"status":null,"gap":null,"points":null},{"code":"LAT","ref":"latifi","name":"Nicholas Latifi","team":"Williams","teamId":"williams","color":"#64C4FF","position":16,"grid":null,"status":null,"gap":null,"points":null},{"code":"MSC","ref":"mick_schumacher","name":"Mick Schumacher","team":"Haas F1 Team","teamId":"haas","color":"#B6BABD","position":17,"grid":null,"status":null,"gap":null,"points":null},{"code":"MAZ","ref":"mazepin","name":"Nikita Mazepin","team":"Haas F1 Team","teamId":"haas","color":"#B6BABD","position":18,"grid":null,"status":null,"gap":null,"points":null},{"code":"STR","ref":"stroll","name":"Lance Stroll","team":"Aston Martin","teamId":"aston","color":"#229971","position":19,"grid":null,"status":null,"gap":null,"points":null},{"code":"GIO","ref":"giovinazzi","name":"Antonio Giovinazzi","team":"Alfa Romeo Racing","teamId":"alfa","color":"#888888","position":20,"grid":null,"status":null,"gap":null,"points":null}],"weather":{"airMin":25.0,"airMax":27.0,"trackMin":43.7,"trackMax":51.4,"windAvg":1.053,"windDirDeg":200,"rain":false,"samples":[[1.0,27.0,50.7,1.08,0],[2.0,26.9,51.4,1.08,0],[3.0,26.7,50.6,1.44,0],[4.0,26.9,50.6,2.16,0],[5.0,27.0,50.6,1.44,0],[7.0,26.8,49.8,1.08,0],[8.0,26.8,49.8,1.08,0],[9.0,26.6,49.8,1.08,0],[10.0,26.7,49.8,1.08,0],[12.0,26.9,50.9,1.44,0],[13.0,26.9,50.7,1.08,0],[14.0,26.8,50.7,1.44,0],[15.0,26.8,49.8,1.44,0],[17.0,27.0,49.2,1.08,0],[18.0,27.0,48.9,1.08,0],[19.0,26.9,49.6,0.72,0],[20.0,26.9,49.6,0.72,0],[22.0,26.7,49.1,1.08,0],[23.0,26.7,48.9,0.72,0],[24.0,26.7,49.1,1.8,0],[25.0,26.7,49.6,1.8,0],[26.0,26.6,49.5,1.08,0],[28.0,26.6,48.4,1.44,0],[29.0,26.6,48.4,1.08,0],[30.0,26.7,49.6,0.72,0],[31.0,26.8,49.6,0.36,0],[33.0,26.8,49.1,0.36,0],[34.0,26.7,48.7,0.72,0],[35.0,26.7,48.7,1.08,0],[36.0,26.5,48.7,1.08,0],[38.0,26.7,48.9,0.36,0],[39.0,26.7,48.8,0.36,0],[40.0,26.7,48.0,0.36,0],[41.0,26.7,47.9,1.08,0],[43.0,26.5,47.7,1.44,0],[44.0,26.3,46.7,1.08,0],[45.0,26.2,46.7,0.36,0],[46.0,26.0,46.7,1.08,0],[48.0,26.1,47.8,1.08,0],[49.0,26.1,46.8,1.44,0],[50.0,25.9,46.6,1.08,0],[51.0,25.9,46.5,1.08,0],[52.0,25.9,46.5,1.44,0],[54.0,25.9,47.1,1.08,0],[55.0,26.0,47.1,1.08,0],[56.0,25.9,46.9,0.72,0],[57.0,25.7,46.9,0.72,0],[59.0,25.9,47.7,0.72,0],[60.0,25.8,47.1,1.08,0],[61.0,25.7,46.5,1.8,0],[62.0,25.6,46.6,1.44,0],[64.0,25.5,46.4,0.36,0],[65.0,25.6,46.4,0.36,0],[66.0,25.6,45.6,1.44,0],[67.0,25.5,45.8,1.08,0],[69.0,25.6,45.3,0.36,0],[70.0,25.6,46.1,1.08,0],[71.0,25.6,46.1,1.08,0],[72.0,25.6,45.4,1.44,0],[74.0,25.4,45.1,1.08,0],[75.0,25.5,45.1,1.08,0],[76.0,25.4,45.5,1.8,0],[77.0,25.4,45.3,2.16,0],[78.0,25.3,45.3,1.08,0],[80.0,25.2,45.0,1.08,0],[81.0,25.2,45.0,1.08,0],[82.0,25.1,45.3,1.44,0],[83.0,25.0,44.4,0.72,0],[85.0,25.0,44.4,1.08,0],[86.0,25.0,44.4,1.08,0],[87.0,25.0,44.4,0.72,0],[88.0,25.0,44.2,1.08,0],[90.0,25.0,43.9,0.72,0],[91.0,25.1,43.9,1.8,0],[92.0,25.0,43.7,1.08,0],[93.0,25.0,43.7,0.72,0],[95.0,25.1,44.5,0.72,0],[96.0,25.1,43.9,0.36,0],[97.0,25.2,43.9,0.72,0],[98.0,25.2,43.9,0.72,0]]},"results":[{"code":"LEC","q1":102.241,"q2":101.659,"q3":101.218},{"code":"HAM","q1":101.545,"q2":101.634,"q3":101.45},{"code":"VER","q1":101.76,"q2":101.625,"q3":101.563},{"code":"GAS","q1":102.288,"q2":101.932,"q3":101.565},{"code":"SAI","q1":102.121,"q2":101.74,"q3":101.576},{"code":"NOR","q1":102.167,"q2":101.813,"q3":101.747},{"code":"PER","q1":101.968,"q2":101.63,"q3":101.917},{"code":"TSU","q1":102.521,"q2":101.654,"q3":102.211},{"code":"ALO","q1":102.934,"q2":102.195,"q3":102.327},{"code":"BOT","q1":102.701,"q2":102.106,"q3":102.659},{"code":"VET","q1":102.46,"q2":102.224,"q3":null},{"code":"OCO","q1":102.426,"q2":102.273,"q3":null},{"code":"RIC","q1":102.304,"q2":102.558,"q3":null},{"code":"RAI","q1":102.923,"q2":102.587,"q3":null},{"code":"RUS","q1":102.728,"q2":102.758,"q3":null},{"code":"LAT","q1":103.128,"q2":null,"q3":null},{"code":"MSC","q1":104.158,"q2":null,"q3":null},{"code":"MAZ","q1":104.238,"q2":null,"q3":null},{"code":"STR","q1":null,"q2":null,"q3":null},{"code":"GIO","q1":null,"q2":null,"q3":null}],"sectors":[{"code":"LEC","lap":101.218,"s":[35.502,40.555,25.161],"bs":[35.413,40.555,25.161],"st":314.0,"fl":331.0},{"code":"HAM","lap":101.45,"s":[35.533,40.683,25.234],"bs":[35.508,40.683,25.018],"st":313.0,"fl":333.0},{"code":"VER","lap":101.563,"s":[35.635,40.592,25.336],"bs":[35.365,40.525,25.31],"st":313.0,"fl":325.0},{"code":"GAS","lap":101.565,"s":[35.432,40.598,25.535],"bs":[35.432,40.598,25.426],"st":309.0,"fl":326.0},{"code":"SAI","lap":101.576,"s":[35.485,40.672,25.419],"bs":[35.478,40.672,25.195],"st":311.0,"fl":325.0},{"code":"PER","lap":101.63,"s":[35.534,40.72,25.376],"bs":[35.534,40.72,25.281],"st":313.0,"fl":327.0},{"code":"TSU","lap":101.654,"s":[35.627,40.768,25.259],"bs":[35.627,40.768,25.259],"st":312.0,"fl":331.0},{"code":"NOR","lap":101.747,"s":[35.652,40.641,25.454],"bs":[35.567,40.641,25.365],"st":308.0,"fl":324.0},{"code":"BOT","lap":102.106,"s":[35.735,41.094,25.277],"bs":[35.447,41.082,25.277],"st":310.0,"fl":325.0},{"code":"ALO","lap":102.195,"s":[35.676,41.076,25.443],"bs":[35.676,41.076,25.395],"st":312.0,"fl":330.0},{"code":"VET","lap":102.224,"s":[35.48,41.173,25.571],"bs":[35.48,41.173,25.118],"st":312.0,"fl":323.0},{"code":"OCO","lap":102.273,"s":[35.842,41.104,25.327],"bs":[35.83,41.096,25.327],"st":313.0,"fl":331.0},{"code":"RIC","lap":102.304,"s":[35.646,41.218,25.44],"bs":[35.646,41.218,25.44],"st":309.0,"fl":326.0},{"code":"RAI","lap":102.587,"s":[35.986,41.22,25.381],"bs":[35.919,41.22,25.249],"st":311.0,"fl":326.0},{"code":"RUS","lap":102.728,"s":[36.133,41.321,25.274],"bs":[36.028,41.321,25.274],"st":314.0,"fl":330.0},{"code":"LAT","lap":103.128,"s":[36.312,41.57,25.246],"bs":[36.248,41.57,25.246],"st":312.0,"fl":329.0},{"code":"MSC","lap":104.158,"s":[36.542,42.044,25.572],"bs":[36.542,41.961,25.499],"st":309.0,"fl":327.0},{"code":"MAZ","lap":104.238,"s":[36.117,41.948,26.173],"bs":[36.117,41.948,25.52],"st":308.0,"fl":323.0}],"lapsAll":{"ALO":[[32.58,102.934,"S",0],[47.07,102.947,"S",0],[48.79,134.207,"S",0],[51.03,120.598,"S",0],[63.29,102.195,"S",0],[86.84,102.327,"S",0]],"BOT":[[46.76,102.701,"S",0],[48.47,135.826,"S",0],[50.74,114.971,"S",0],[63.66,124.9,"S",0],[65.74,102.106,"S",0],[86.03,116.741,"S",0],[87.98,102.659,"S",0]],"GAS":[[46.37,102.434,"S",0],[48.08,136.292,"S",0],[50.35,102.288,"S",0],[66.6,101.932,"S",0],[68.3,133.834,"S",0],[70.53,102.811,"S",0],[91.42,101.565,"S",0],[93.12,148.751,"S",0]],"HAM":[[46.62,102.161,"S",0],[48.32,130.703,"S",0],[50.5,101.545,"S",0],[63.76,113.615,"S",0],[65.65,101.634,"S",0],[86.11,115.184,"S",0],[88.03,101.45,"S",0]],"LAT":[[46.05,103.128,"S",0],[47.77,139.811,"S",0],[50.1,103.284,"S",0]],"LEC":[[17.2,102.532,"S",0],[32.51,102.241,"S",0],[47.13,108.704,"S",0],[63.65,101.659,"S",0],[86.38,101.218,"S",0]],"MAZ":[[32.19,104.281,"S",0],[46.67,104.238,"S",0],[48.4,133.051,"S",0]],"MSC":[[32.02,104.254,"S",0],[46.2,104.434,"S",0],[47.95,137.476,"S",0],[50.24,104.158,"S",0]],"NOR":[[46.9,103.11,"S",0],[48.62,136.945,"S",0],[50.91,117.533,"S",0],[52.86,102.167,"S",0],[63.52,101.813,"S",0],[86.63,101.747,"S",0]],"OCO":[[32.42,102.426,"S",0],[63.38,102.273,"S",0],[71.7,102.516,"S",0]],"PER":[[32.73,101.968,"S",0],[47.42,105.115,"S",0],[63.16,101.63,"S",0],[86.71,101.917,"S",0]],"RAI":[[46.53,103.076,"S",0],[48.25,139.57,"S",0],[50.57,102.923,"S",0],[66.36,102.71,"S",0],[68.07,138.982,"S",0],[70.38,102.587,"S",0],[72.09,139.405,"S",0]],"RIC":[[46.99,102.304,"S",0],[48.7,136.493,"S",0],[50.97,119.873,"S",0],[63.86,102.558,"S",0]],"RUS":[[32.15,104.18,"S",0],[46.16,103.778,"S",0],[47.89,138.925,"S",0],[50.2,102.728,"S",0],[69.88,102.758,"S",0],[71.59,133.692,"S",0]],"SAI":[[32.32,102.121,"S",0],[47.25,102.255,"S",0],[63.09,101.74,"S",0],[86.5,101.576,"S",0]],"TSU":[[46.47,102.877,"S",0],[48.19,134.597,"S",0],[50.43,102.521,"S",0],[66.29,102.502,"S",0],[68.0,122.438,"S",0],[70.04,101.654,"S",0],[91.35,102.211,"S",0],[93.06,144.441,"S",0]],"VER":[[32.66,101.76,"S",0],[47.32,102.119,"S",0],[63.23,101.756,"S",0],[64.93,125.734,"S",0],[67.03,101.625,"S",0],[86.78,101.563,"S",0]],"VET":[[32.86,102.726,"S",0],[47.54,103.028,"S",0],[49.25,132.762,"S",0],[51.47,102.46,"S",0],[62.99,102.224,"S",0]]},"raceControl":[{"lap":null,"time":"11:45","cat":"Other","flag":null,"msg":"RISK OF RAIN FOR F1 QUALIFYING SESSION IS 0%"},{"lap":null,"time":"11:45","cat":"Other","flag":null,"msg":"RISK OF RAIN FOR F1 QUALIFYING SESSION IS 0%"},{"lap":null,"time":"11:00","cat":"Other","flag":null,"msg":"AIR TEMPERATURE 1 HOUR BEFORE Q1 = 27 DEGREES"},{"lap":null,"time":"11:45","cat":"Other","flag":null,"msg":"RISK OF RAIN FOR F1 QUALIFYING SESSION IS 0%"},{"lap":null,"time":"12:00","cat":"Flag","flag":"GREEN","msg":"GREEN LIGHT - PIT EXIT OPEN"},{"lap":null,"time":"12:03","cat":"Flag","flag":"YELLOW","msg":"YELLOW IN TRACK SECTOR 17"},{"lap":null,"time":"12:03","cat":"Flag","flag":"DOUBLE YELLOW","msg":"DOUBLE YELLOW IN TRACK SECTOR 17"},{"lap":null,"time":"12:03","cat":"Flag","flag":"RED","msg":"RED FLAG"},{"lap":null,"time":"12:03","cat":"Flag","flag":"CLEAR","msg":"CLEAR IN TRACK SECTOR 17"},{"lap":null,"time":"12:05","cat":"Other","flag":null,"msg":"MEDICAL CAR DEPLOYED"},{"lap":null,"time":"12:13","cat":"Other","flag":null,"msg":"SESSION WILL RE-START AT 16:15"},{"lap":null,"time":"12:13","cat":"Flag","flag":"CLEAR","msg":"TRACK CLEAR"},{"lap":null,"time":"12:13","cat":"Drs","flag":null,"msg":"DRS ENABLED"},{"lap":null,"time":"12:15","cat":"Flag","flag":"GREEN","msg":"GREEN LIGHT - PIT EXIT OPEN"},{"lap":null,"time":"12:19","cat":"Flag","flag":"YELLOW","msg":"YELLOW IN TRACK SECTOR 15"},{"lap":null,"time":"12:19","cat":"Flag","flag":"DOUBLE YELLOW","msg":"DOUBLE YELLOW IN TRACK SECTOR 16"},{"lap":null,"time":"12:19","cat":"Flag","flag":"RED","msg":"RED FLAG"},{"lap":null,"time":"12:19","cat":"Flag","flag":"CLEAR","msg":"CLEAR IN TRACK SECTOR 15"},{"lap":null,"time":"12:19","cat":"Flag","flag":"CLEAR","msg":"CLEAR IN TRACK SECTOR 16"},{"lap":null,"time":"12:21","cat":"Other","flag":null,"msg":"MEDICAL CAR DEPLOYED"},{"lap":null,"time":"12:27","cat":"Other","flag":null,"msg":"SESSION WILL RE-START AT 16:29"},{"lap":null,"time":"12:27","cat":"Flag","flag":"CLEAR","msg":"TRACK CLEAR"},{"lap":null,"time":"12:27","cat":"Drs","flag":null,"msg":"DRS ENABLED"},{"lap":null,"time":"12:29","cat":"Flag","flag":"GREEN","msg":"GREEN LIGHT - PIT EXIT OPEN"},{"lap":null,"time":"12:30","cat":"Other","flag":null,"msg":"CAR 4 (NOR) WILL BE INVESTIGATED AFTER THE SESSION - RED FLAG PROCEDURES"},{"lap":null,"time":"12:36","cat":"Flag","flag":"YELLOW","msg":"YELLOW IN TRACK SECTOR 5"},{"lap":null,"time":"12:36","cat":"Other","flag":null,"msg":"DRS DISABLED IN ZONE 1"},{"lap":null,"time":"12:36","cat":"Other","flag":null,"msg":"DRS ENABLED IN ZONE 1"},{"lap":null,"time":"12:36","cat":"Flag","flag":"CLEAR","msg":"CLEAR IN TRACK SECTOR 5"},{"lap":null,"time":"12:36","cat":"CarEvent","flag":null,"msg":"CAR 9 (MAZ) OFF TRACK AND CONTINUED AT TURN 3"},{"lap":null,"time":"12:37","cat":"Other","flag":null,"msg":"TRACK SURFACE SLIPPERY IN TRACK SECTOR 6"},{"lap":null,"time":"12:37","cat":"Flag","flag":"CLEAR","msg":"CLEAR IN TRACK SECTOR 6"},{"lap":null,"time":"12:38","cat":"Flag","flag":"CHEQUERED","msg":"CHEQUERED FLAG"},{"lap":null,"time":"12:40","cat":"Other","flag":null,"msg":"Q2 WILL START AT 16:46"},{"lap":null,"time":"12:42","cat":"Flag","flag":"DOUBLE YELLOW","msg":"DOUBLE YELLOW IN TRACK SECTOR 3"},{"lap":null,"time":"12:42","cat":"Other","flag":null,"msg":"DRS DISABLED IN ZONE 1"},{"lap":null,"time":"12:42","cat":"Flag","flag":"DOUBLE YELLOW","msg":"DOUBLE YELLOW IN TRACK SECTOR 18"},{"lap":null,"time":"12:43","cat":"Flag","flag":"CLEAR","msg":"CLEAR IN TRACK SECTOR 3"},{"lap":null,"time":"12:43","cat":"Other","flag":null,"msg":"DRS ENABLED IN ZONE 1"},{"lap":null,"time":"12:43","cat":"Flag","flag":"YELLOW","msg":"YELLOW IN TRACK SECTOR 17"},{"lap":null,"time":"12:43","cat":"Flag","flag":"CLEAR","msg":"CLEAR IN TRACK SECTOR 18"},{"lap":null,"time":"12:43","cat":"Flag","flag":"CLEAR","msg":"CLEAR IN TRACK SECTOR 17"},{"lap":null,"time":"12:46","cat":"Flag","flag":"GREEN","msg":"GREEN LIGHT - PIT EXIT OPEN"},{"lap":null,"time":"12:59","cat":"Flag","flag":"YELLOW","msg":"YELLOW IN TRACK SECTOR 5"},{"lap":null,"time":"12:59","cat":"Other","flag":null,"msg":"DRS DISABLED IN ZONE 1"},{"lap":null,"time":"12:59","cat":"Flag","flag":"RED","msg":"RED FLAG"},{"lap":null,"time":"12:59","cat":"Flag","flag":"CLEAR","msg":"CLEAR IN TRACK SECTOR 5"},{"lap":null,"time":"12:59","cat":"Other","flag":null,"msg":"SESSION WILL NOT BE RESTARTED"},{"lap":null,"time":"13:02","cat":"Other","flag":null,"msg":"MEDICAL CAR DEPLOYED"},{"lap":null,"time":"13:04","cat":"Other","flag":null,"msg":"Q3 WILL START AT 17:09"},{"lap":null,"time":"13:05","cat":"Flag","flag":"CLEAR","msg":"TRACK CLEAR"},{"lap":null,"time":"13:05","cat":"Drs","flag":null,"msg":"DRS ENABLED"},{"lap":null,"time":"13:09","cat":"Flag","flag":"GREEN","msg":"GREEN LIGHT - PIT EXIT OPEN"},{"lap":null,"time":"13:20","cat":"Flag","flag":"YELLOW","msg":"YELLOW IN TRACK SECTOR 5"},{"lap":null,"time":"13:20","cat":"Other","flag":null,"msg":"DRS DISABLED IN ZONE 1"},{"lap":null,"time":"13:20","cat":"Flag","flag":"RED","msg":"RED FLAG"},{"lap":null,"time":"13:21","cat":"Flag","flag":"CLEAR","msg":"CLEAR IN TRACK SECTOR 5"},{"lap":null,"time":"13:22","cat":"Other","flag":null,"msg":"SESSION WILL NOT BE RESTARTED"},{"lap":null,"time":"13:25","cat":"Flag","flag":"CLEAR","msg":"TRACK CLEAR"},{"lap":null,"time":"13:25","cat":"Other","flag":null,"msg":"RISK OF RAIN FOR F2 SECOND RACE IS 0%"},{"lap":null,"time":"13:26","cat":"Flag","flag":"DOUBLE YELLOW","msg":"DOUBLE YELLOW IN TRACK SECTOR 5"},{"lap":null,"time":"13:26","cat":"Other","flag":null,"msg":"TRACK SURFACE SLIPPERY IN TRACK SECTOR 18"},{"lap":null,"time":"13:26","cat":"Flag","flag":"CLEAR","msg":"CLEAR IN TRACK SECTOR 18"},{"lap":null,"time":"13:27","cat":"Flag","flag":"DOUBLE YELLOW","msg":"DOUBLE YELLOW IN TRACK SECTOR 10"},{"lap":null,"time":"13:27","cat":"Flag","flag":"DOUBLE YELLOW","msg":"DOUBLE YELLOW IN TRACK SECTOR 3"},{"lap":null,"time":"13:27","cat":"Flag","flag":"DOUBLE YELLOW","msg":"DOUBLE YELLOW IN TRACK SECTOR 18"},{"lap":null,"time":"13:27","cat":"Flag","flag":"CLEAR","msg":"CLEAR IN TRACK SECTOR 10"},{"lap":null,"time":"13:27","cat":"Flag","flag":"CLEAR","msg":"CLEAR IN TRACK SECTOR 3"},{"lap":null,"time":"13:27","cat":"Flag","flag":"YELLOW","msg":"YELLOW IN TRACK SECTOR 17"},{"lap":null,"time":"13:27","cat":"Flag","flag":"CLEAR","msg":"CLEAR IN TRACK SECTOR 18"},{"lap":null,"time":"13:28","cat":"Flag","flag":"CLEAR","msg":"CLEAR IN TRACK SECTOR 17"},{"lap":null,"time":"13:36","cat":"Other","flag":null,"msg":"DRS DISABLED IN ZONE 1"}],"poleTel":{"a":"LEC","b":"HAM","step":14.877,"len":5950.67,"speedA":[324.0,324.0,324.0,324.0,324.0,324.0,324.0,324.0,323.4,323.0,323.0,323.0,322.6,320.1,298.4,258.6,224.1,193.7,157.3,138.5,126.6,124.0,133.4,145.4,162.3,171.8,189.7,199.3,209.3,216.0,223.4,229.3,234.0,239.2,243.9,247.8,251.2,252.9,254.4,213.8,172.5,140.1,115.0,102.3,99.9,110.3,130.0,153.4,168.0,181.7,196.2,201.9,217.1,224.1,229.9,238.3,243.2,249.9,254.5,257.5,261.1,265.9,270.1,274.2,276.3,278.3,281.0,284.0,284.8,287.3,289.7,291.5,294.5,296.3,297.8,299.3,300.8,302.1,303.6,305.7,306.6,307.7,309.1,309.8,310.5,311.5,312.9,313.7,314.0,314.2,315.6,316.0,315.8,315.1,315.0,296.0,257.3,225.4,190.4,153.9,124.6,108.4,106.1,115.4,130.5,149.8,165.9,181.3,191.6,199.9,207.5,214.8,213.0,183.0,155.1,122.8,100.2,89.2,97.8,111.5,134.5,157.5,170.7,184.5,195.0,205.7,214.1,219.8,224.7,232.1,237.6,242.2,245.8,248.5,250.5,225.7,183.8,157.4,133.9,120.7,111.3,106.9,108.1,95.4,98.2,110.0,125.3,144.6,160.6,176.8,187.7,195.3,206.0,210.6,224.3,230.3,234.3,240.3,244.0,249.6,253.9,256.0,258.7,261.4,248.9,206.0,174.2,135.0,102.4,85.4,76.0,87.9,106.5,125.7,149.3,168.1,179.6,189.4,199.3,205.0,190.7,150.8,127.0,117.5,118.0,135.7,145.2,140.2,110.7,97.5,97.6,108.2,125.8,121.0,118.6,126.5,143.4,159.9,174.0,187.2,198.5,204.5,210.0,220.3,225.6,231.4,236.9,241.6,247.0,249.7,254.7,258.0,260.5,263.8,267.6,270.1,273.3,274.6,275.5,276.5,278.0,278.0,280.7,282.5,283.2,284.1,285.6,287.8,289.7,291.3,293.1,293.8,296.0,297.0,297.0,297.0,299.2,300.0,300.0,300.0,300.6,301.0,300.7,290.7,269.5,241.8,212.8,179.5,146.2,115.0,95.0,94.1,109.6,129.7,154.3,170.1,184.6,195.0,206.4,214.7,224.2,227.6,231.9,238.7,245.4,249.5,252.6,254.5,253.0,227.4,186.3,159.8,138.4,129.0,123.5,127.9,137.3,151.7,164.8,178.8,191.3,204.6,211.9,218.6,224.0,231.1,238.0,242.5,246.7,250.7,254.6,259.1,264.1,265.7,268.8,272.1,274.7,276.7,280.7,281.9,284.0,285.8,287.0,287.0,288.3,289.0,289.0,289.0,289.9,291.3,292.0,292.3,292.9,292.1,292.5,293.2,294.0,294.0,294.5,295.3,296.0,297.5,299.0,300.7,302.9,303.0,303.0,303.2,303.9,305.3,306.8,308.1,308.8,309.0,309.3,310.0,310.7,310.6,310.0,310.7,311.4,312.0,312.0,312.0,312.9,313.8,313.1,313.6,314.0,314.0,314.0,314.4,315.0,315.0,315.5,316.0,316.0,316.5,317.2,317.9,318.0,318.0,318.0,318.0,318.4,319.6,320.9,322.3,323.7,324.0,324.5,325.8,325.4,325.3,326.0,326.7,327.3,328.0,328.0,328.0,328.0,328.0,328.0,328.0,328.6,328.6,328.1,328.8,329.0,329.2,329.8,329.5,329.2,329.8,330.0,330.0,330.0,330.8,332.1,332.8],"speedB":[328.6,329.2,329.9,329.4,329.5,330.6,331.5,331.9,331.2,330.5,329.8,329.2,328.0,319.8,293.3,242.9,208.7,169.7,147.2,129.8,120.0,123.8,136.1,157.4,171.4,178.4,195.1,203.3,213.3,220.0,225.2,231.0,236.8,243.2,246.8,248.7,251.2,250.8,232.0,201.9,164.9,128.4,106.5,95.3,99.9,117.3,133.7,152.5,172.5,184.2,196.8,206.6,215.5,225.0,231.3,237.7,243.1,246.9,253.1,259.1,262.5,267.3,270.6,273.8,277.3,278.9,282.0,285.7,288.6,290.2,291.7,293.8,295.0,295.8,301.1,303.3,304.9,306.1,307.6,308.5,309.5,310.9,313.0,314.4,315.1,316.6,317.0,317.4,318.8,319.6,320.0,320.0,320.7,320.6,316.9,285.5,254.4,211.7,176.4,143.7,115.8,102.4,101.7,117.6,131.9,156.8,170.3,184.4,195.0,204.6,215.0,216.5,192.0,162.3,129.0,106.5,89.4,92.6,108.7,130.5,149.3,168.4,183.9,195.6,203.1,210.3,219.0,225.9,232.0,235.8,239.7,244.2,248.7,249.8,231.6,203.4,167.8,150.9,127.9,118.7,106.9,108.4,97.3,90.9,101.7,119.4,145.3,164.4,179.1,191.5,200.5,210.9,212.0,226.1,231.6,236.3,242.5,246.7,251.4,255.3,257.6,259.7,262.8,254.9,215.8,180.7,150.1,110.8,86.7,74.7,79.1,95.3,120.8,141.2,161.1,175.4,185.2,193.3,200.8,198.5,168.0,140.0,116.7,110.8,126.5,143.8,148.6,127.0,106.7,96.1,102.5,114.1,115.5,110.8,117.9,128.0,145.0,161.8,175.4,188.7,198.6,209.2,215.5,222.6,229.2,232.3,240.6,245.3,249.8,253.6,257.1,260.5,263.9,267.3,271.4,273.4,275.5,277.6,279.1,279.9,280.7,281.0,281.5,284.6,286.4,287.9,289.5,291.0,292.8,293.7,294.9,296.2,297.0,297.7,298.9,299.8,299.1,299.7,300.4,301.2,301.9,299.4,284.8,255.2,220.2,197.1,170.0,147.1,116.2,98.9,92.8,104.8,126.3,149.2,168.2,181.4,195.3,204.8,216.1,222.1,229.0,236.6,238.8,246.2,250.7,253.7,257.2,260.3,254.8,217.5,187.2,157.8,138.1,128.0,121.2,127.4,136.1,140.3,158.6,179.2,187.7,197.4,212.0,218.1,224.0,229.0,238.4,243.3,248.5,252.6,256.6,260.9,264.7,267.3,271.4,274.1,276.5,279.2,282.1,282.9,284.3,285.0,285.5,287.0,287.0,287.0,288.0,289.6,291.0,291.8,292.6,293.3,293.9,294.0,293.6,293.2,294.0,294.7,295.0,296.2,299.9,300.0,300.9,302.4,303.9,304.7,305.4,306.1,306.9,307.6,308.3,309.0,309.0,309.5,310.0,310.0,310.6,310.6,310.2,311.0,311.0,311.4,312.1,312.8,313.0,313.0,313.0,313.7,314.0,314.1,314.8,314.5,314.2,314.9,315.0,315.0,315.1,315.8,316.0,316.2,316.9,317.0,317.3,318.0,318.7,319.8,321.2,322.5,323.5,324.1,324.8,326.0,327.0,327.0,327.6,328.2,328.9,329.0,329.0,329.0,329.0,329.4,330.2,330.8,331.0,330.8,330.1,329.5,329.2,329.9,330.6,331.0,331.0,331.0,331.2,331.8,332.4,333.1,333.8,334.0],"delta":[0.0,-0.003,-0.006,-0.009,-0.012,-0.016,-0.02,-0.024,-0.028,-0.032,-0.036,-0.039,-0.042,-0.043,-0.042,-0.033,-0.019,0.017,0.047,0.073,0.094,0.1,0.097,0.074,0.05,0.035,0.026,0.017,0.012,0.008,0.005,0.004,0.002,-0.001,-0.004,-0.006,-0.007,-0.005,0.01,0.023,0.026,0.052,0.09,0.13,0.15,0.132,0.113,0.105,0.092,0.086,0.084,0.079,0.078,0.078,0.076,0.077,0.077,0.08,0.081,0.08,0.078,0.077,0.076,0.076,0.075,0.074,0.073,0.072,0.069,0.067,0.066,0.064,0.063,0.063,0.062,0.059,0.057,0.054,0.051,0.05,0.048,0.046,0.043,0.04,0.038,0.035,0.032,0.03,0.027,0.024,0.021,0.019,0.016,0.013,0.012,0.018,0.024,0.035,0.056,0.074,0.108,0.143,0.166,0.162,0.158,0.151,0.142,0.14,0.135,0.129,0.12,0.116,0.133,0.171,0.235,0.302,0.368,0.384,0.333,0.262,0.221,0.191,0.169,0.148,0.134,0.125,0.118,0.112,0.104,0.099,0.097,0.095,0.093,0.091,0.107,0.134,0.165,0.185,0.201,0.207,0.22,0.216,0.255,0.301,0.286,0.266,0.209,0.155,0.114,0.087,0.067,0.049,0.039,0.024,0.014,0.007,-0.001,-0.009,-0.016,-0.022,-0.025,-0.028,-0.031,-0.028,-0.006,0.025,0.066,0.14,0.222,0.312,0.311,0.266,0.203,0.137,0.109,0.093,0.084,0.077,0.074,0.076,0.111,0.143,0.174,0.207,0.19,0.158,0.144,0.169,0.19,0.202,0.179,0.153,0.17,0.212,0.227,0.221,0.215,0.207,0.205,0.204,0.204,0.201,0.195,0.193,0.189,0.187,0.183,0.178,0.175,0.171,0.169,0.167,0.165,0.163,0.16,0.157,0.155,0.153,0.15,0.147,0.145,0.143,0.142,0.14,0.138,0.135,0.133,0.131,0.129,0.127,0.126,0.124,0.123,0.122,0.121,0.119,0.118,0.118,0.118,0.117,0.116,0.117,0.124,0.143,0.186,0.237,0.301,0.367,0.447,0.526,0.562,0.516,0.441,0.378,0.341,0.321,0.309,0.295,0.282,0.272,0.265,0.256,0.248,0.241,0.237,0.233,0.23,0.225,0.22,0.231,0.243,0.248,0.252,0.256,0.262,0.265,0.267,0.285,0.297,0.295,0.297,0.306,0.309,0.31,0.311,0.313,0.311,0.309,0.307,0.305,0.303,0.301,0.301,0.3,0.298,0.296,0.295,0.293,0.292,0.291,0.29,0.29,0.291,0.291,0.291,0.292,0.293,0.292,0.292,0.291,0.291,0.29,0.289,0.287,0.287,0.286,0.286,0.285,0.285,0.284,0.282,0.28,0.279,0.278,0.277,0.275,0.274,0.272,0.27,0.268,0.267,0.266,0.266,0.265,0.265,0.264,0.264,0.264,0.264,0.263,0.263,0.264,0.263,0.262,0.262,0.262,0.262,0.262,0.262,0.261,0.261,0.26,0.26,0.26,0.26,0.261,0.261,0.261,0.261,0.262,0.262,0.263,0.263,0.263,0.262,0.262,0.262,0.261,0.261,0.261,0.26,0.26,0.259,0.258,0.257,0.256,0.255,0.254,0.253,0.252,0.252,0.251,0.249,0.248,0.246,0.245,0.244,0.243,0.243,0.242,0.242,0.241,0.24,0.239,0.238,0.237,0.235,0.234,0.233,0.232],"corners":[{"name":"T1","d":303.767},{"name":"T2","d":644.74},{"name":"T3","d":1512.33},{"name":"T4","d":1739.819},{"name":"T5","d":2077.152},{"name":"T6","d":2133.749},{"name":"T7","d":2520.548},{"name":"T8","d":2714.735},{"name":"T9","d":2736.211},{"name":"T10","d":2770.148},{"name":"T11","d":2817.157},{"name":"T12","d":2872.628},{"name":"T13","d":3279.04},{"name":"T14","d":3509.453},{"name":"T15","d":3716.287},{"name":"T16","d":4084.609},{"name":"T17","d":4269.067},{"name":"T18","d":4517.965},{"name":"T19","d":4660.166},{"name":"T20","d":4971.359}]},"dominance":{"n":25,"codes":["LEC","HAM","VER"],"owners":["VER","VER","LEC","HAM","HAM","HAM","LEC","HAM","LEC","HAM","LEC","VER","LEC","HAM","HAM","LEC","VER","LEC","HAM","HAM","HAM","LEC","LEC","HAM","HAM"]},"track":{"pts":[[829.9,221.1],[839.9,217.5],[850.0,214.0],[860.0,210.4],[870.0,206.8],[880.0,203.1],[890.0,199.6],[900.1,196.0],[910.0,192.3],[920.2,188.6],[931.0,185.4],[940.6,181.5],[947.5,174.9],[950.0,165.4],[947.3,154.6],[943.2,144.5],[939.6,134.6],[935.9,124.6],[932.1,114.8],[928.3,104.9],[924.5,95.0],[920.8,85.1],[917.1,75.5],[913.3,65.7],[909.4,55.4],[905.2,45.5],[898.1,40.0],[887.1,42.0],[877.2,45.4],[868.3,48.4],[858.1,51.5],[847.9,54.6],[837.9,57.8],[827.8,61.0],[817.8,64.1],[807.7,67.3],[797.6,70.6],[787.5,73.8],[777.4,76.9],[767.3,80.2],[757.3,83.7],[747.3,87.3],[737.4,91.0],[727.4,94.7],[717.4,98.4],[707.4,102.2],[697.5,105.8],[687.6,109.5],[677.6,113.2],[667.7,116.8],[657.7,120.6],[647.7,124.3],[637.8,128.1],[627.8,132.0],[617.9,135.8],[608.0,139.6],[598.1,143.4],[587.7,147.3],[577.6,151.3],[568.2,154.9],[558.4,159.2],[552.0,165.6],[553.7,176.0],[558.5,186.1],[561.8,196.0],[564.5,206.3],[567.9,216.4],[572.0,226.4],[575.9,236.4],[579.0,246.9],[578.0,256.4],[569.3,262.4],[558.3,265.9],[547.9,269.2],[538.1,272.9],[528.2,276.5],[518.2,280.1],[508.4,284.4],[499.0,289.2],[489.8,294.1],[480.6,298.9],[470.7,303.7],[461.3,308.9],[453.9,316.0],[451.7,325.4],[456.0,336.0],[455.0,345.2],[445.5,351.6],[435.5,356.9],[426.7,362.9],[418.1,369.1],[409.3,375.0],[400.6,380.8],[391.9,386.8],[383.1,392.8],[374.3,398.8],[365.3,404.9],[356.2,411.1],[347.1,417.2],[338.1,423.5],[329.4,429.8],[320.4,434.2],[312.7,430.1],[309.0,419.1],[306.6,408.8],[304.2,398.8],[300.9,385.4],[298.4,375.3],[295.8,364.7],[293.0,354.1],[284.5,348.3],[274.6,344.7],[263.8,343.0],[253.6,340.5],[247.1,333.3],[246.7,321.8],[239.2,316.3],[228.0,316.5],[217.6,318.3],[205.4,322.4],[195.6,326.4],[185.7,329.9],[175.8,333.7],[166.2,338.0],[156.5,342.4],[146.8,346.6],[137.1,350.9],[127.6,355.6],[118.2,360.4],[108.7,365.2],[99.0,369.9],[90.1,375.0],[83.2,382.6],[78.2,392.4],[74.2,402.5],[70.6,412.6],[67.1,422.6],[63.3,432.5],[59.5,442.4],[56.2,452.7],[53.8,463.1],[52.4,473.6],[52.1,484.3],[52.4,495.0],[52.6,505.6],[53.0,516.4],[53.1,527.3],[52.1,537.8],[50.5,548.8],[50.0,559.5],[56.1,567.0],[65.8,572.2],[74.8,577.5],[83.8,582.7],[93.0,587.8],[102.2,593.1],[111.2,598.7],[120.0,604.5],[128.9,610.3],[138.0,615.7],[147.6,621.4],[156.4,627.2],[165.8,632.6],[175.8,635.9],[185.1,634.1],[192.2,625.7],[197.6,616.0],[202.7,606.7],[208.0,597.2],[213.1,588.0],[218.6,579.0],[224.6,570.4],[231.2,562.1],[238.6,554.5],[246.6,547.6],[255.0,541.0],[263.4,534.5],[271.6,527.8],[279.2,520.5],[286.9,513.2],[295.8,505.9],[303.0,498.5],[308.5,489.5],[312.7,479.4],[315.9,469.2],[318.7,458.9],[321.8,448.8],[326.4,439.8],[333.4,431.8],[342.1,425.1],[351.5,419.0],[360.5,413.2],[369.2,407.2],[378.0,401.1],[386.7,395.1],[395.5,389.2],[404.3,383.1],[413.1,377.2],[421.9,371.2],[430.6,365.1],[439.4,359.3],[448.8,354.3],[459.3,349.8],[469.4,346.2],[479.5,342.8],[489.5,339.4],[499.6,336.0],[509.6,332.5],[519.7,329.0],[529.4,325.6],[539.2,322.1],[549.1,318.6],[559.1,315.0],[569.1,311.5],[579.1,307.9],[589.1,304.3],[599.0,300.6],[609.0,297.0],[619.0,293.4],[629.0,289.8],[639.0,286.2],[649.0,282.5],[659.0,278.9],[669.0,275.3],[678.9,271.7],[688.9,268.1],[698.9,264.5],[709.0,261.1],[719.1,257.9],[729.3,254.8],[739.4,251.5],[749.6,248.3],[759.7,245.1],[769.8,242.0],[780.0,238.8],[790.1,235.4],[800.1,231.9],[810.0,228.2],[819.8,224.7],[829.8,221.1]],"len":5950.67}}
